Workbook

Sheet Resumen
A1: MedicalSys — Proyecto de Seguridad de Sistemas (SIS 321)
A2: Plan del sprint sáb 10 → mar 13 (entrega 1) → jue 15 (entrega 2) · Equipo Linear: Los 6 Siniestros
A4: Objetivo del sprint
A5: El martes 13 por la mañana presentamos MedicalSys con su seguridad FUNCIONANDO EN VIVO (usuarios, roles y contraseñas, corrección OWASP, logs de seguridad, escaneo antes/después, criptografía e integridad) y el informe SIS 321 completo con sus anexos GRC. El jueves 15 entregamos los detalles pendientes (entrega 2).
A7: Avance general | B7: =IFERROR(COUNTIF(Tareas!$S$5:$S$77,"Hecha")/(COUNTA(Tareas!$A$5:$A$77)-COUNTIF(Tareas!$S$5:$S$77,"Cancelada")),0) | C7: Tareas hechas / tareas vigentes (calculado desde la hoja Tareas)
A8: Tareas en total | B8: =COUNTA(Tareas!$A$5:$A$77)
A9: Horas estimadas en total | B9: =SUM(Tareas!$M$5:$M$77)
A10: Bloqueadas ahora | B10: =COUNTIF(Tareas!$S$5:$S$77,"Bloqueada")
A11: Proyecto en Linear | B11: https://linear.app/los-5-furiosos/project/medicalsys-proyecto-seguridad-sis-321-d51e6b35ec22
A13: Equipo y frentes de trabajo
A14: Persona | B14: Rol | C14: Frente (secciones del informe) | D14: Tareas | E14: Horas | F14: Hechas | G14: % avance
A15: Nicole | B15: Tech Lead / Scrum Master | C15: Identidad y Keycloak (9.1, 9.3), code freeze, sección 9.1/9.3 | D15: =COUNTIF(Tareas!$D$5:$D$77,A15) | E15: =SUMIF(Tareas!$D$5:$D$77,A15,Tareas!$M$5:$M$77) | F15: =COUNTIFS(Tareas!$D$5:$D$77,A15,Tareas!$S$5:$S$77,"Hecha") | G15: =IFERROR(F15/D15,0)
A16: Franco | B16: Desarrollador | C16: Roles y autorización granular (9.2), principios de diseño seguro (10) | D16: =COUNTIF(Tareas!$D$5:$D$77,A16) | E16: =SUMIF(Tareas!$D$5:$D$77,A16,Tareas!$M$5:$M$77) | F16: =COUNTIFS(Tareas!$D$5:$D$77,A16,Tareas!$S$5:$S$77,"Hecha") | G16: =IFERROR(F16/D16,0)
A17: Juanjo | B17: Desarrollador | C17: Hardening OWASP (11), escaneo de vulnerabilidades (13), despliegue público | D17: =COUNTIF(Tareas!$D$5:$D$77,A17) | E17: =SUMIF(Tareas!$D$5:$D$77,A17,Tareas!$M$5:$M$77) | F17: =COUNTIFS(Tareas!$D$5:$D$77,A17,Tareas!$S$5:$S$77,"Hecha") | G17: =IFERROR(F17/D17,0)
A18: Alvaro | B18: Desarrollador | C18: Criptografía, integridad por hash/checksum, logs de seguridad (12) | D18: =COUNTIF(Tareas!$D$5:$D$77,A18) | E18: =SUMIF(Tareas!$D$5:$D$77,A18,Tareas!$M$5:$M$77) | F18: =COUNTIFS(Tareas!$D$5:$D$77,A18,Tareas!$S$5:$S$77,"Hecha") | G18: =IFERROR(F18/D18,0)
A19: Alan | B19: Analista GRC / Editor del informe | C19: ISO 27002 2022 y 2013, fichas de brechas, riesgos y KRIs (14), consolidación del informe | D19: =COUNTIF(Tareas!$D$5:$D$77,A19) | E19: =SUMIF(Tareas!$D$5:$D$77,A19,Tareas!$M$5:$M$77) | F19: =COUNTIFS(Tareas!$D$5:$D$77,A19,Tareas!$S$5:$S$77,"Hecha") | G19: =IFERROR(F19/D19,0)
A20: Favian | B20: Analista GRC | C20: Clasificación de la información, políticas generales, gestor de contraseñas, módulo 15, presentación y póster | D20: =COUNTIF(Tareas!$D$5:$D$77,A20) | E20: =SUMIF(Tareas!$D$5:$D$77,A20,Tareas!$M$5:$M$77) | F20: =COUNTIFS(Tareas!$D$5:$D$77,A20,Tareas!$S$5:$S$77,"Hecha") | G20: =IFERROR(F20/D20,0)
A22: Hitos
A23: Cuándo | B23: Hito | C23: Qué tiene que estar listo
A24: Sáb 10 · 09:00 | B24: Kickoff (C-01) | C24: Decisiones registradas en la hoja «Decisiones». Todos con acceso a Linear, repo y carpeta.
A25: Sáb 10 · 11:00 | B25: Plantillas listas | C25: Plantilla del informe (INF-00) y de políticas/procedimientos (GRC-00).
A26: Sáb 10 · 14:00 | B26: Escaneo «antes» | C26: VULN-01 terminado: recién desde aquí se pueden mergear correcciones de seguridad.
A27: Sáb 10 · 18:00 | B27: Go/no-go Keycloak | C27: Si el spike IAM-01 no funciona, se activa el plan B IAM-07 (políticas nativas).
A28: Dom 11 · 22:00 | B28: Backend de seguridad completo | C28: Login con Keycloak, desbloqueo y reinicio, API de roles, autorización por permisos, hardening.
A29: Lun 12 · 18:00 | B29: CODE FREEZE (C-03) | C29: Merge a develop, tag v-seg-1, despliegue estable, smoke test.
A30: Lun 12 · 19:00 | B30: Secciones del informe | C30: INF-02 a INF-08 redactadas; Alan consolida.
A31: Lun 12 · 21:30 | B31: Ensayo de defensa (C-04) | C31: Todos explican todo; banco de preguntas de la hoja «Defensa».
A32: Lun 12 · 23:00 | B32: PDF + presentación | C32: ProyNombreGrupo-1.pdf y PresNombreGrupo-1.pdf; subida al LMS antes de las 23:59.
A33: Mar 13 · 07:00 | B33: Ensayo final | C33: Demo cronometrada (< 8 min) y presentación.
A34: Jue 15 | B34: Entrega 2 | C34: Observaciones del martes, póster y opcionales (IAM-08, HARD-05); archivos -2.pdf.
A36: Reglas de trabajo
A37: • | B37: Dailies de 15 minutos a las 9:00 y a las 21:00. El tablero de Linear es la fuente de verdad: mover la tarea en cuanto cambie de estado.
A38: • | B38: Ramas seg/<ID>-descripcion (ej. seg/RBAC-03-permisos) → PR a develop con revisión cruzada (Nicole↔Franco, Juanjo↔Alvaro).
A39: • | B39: Cada tarea de código deja evidencia ANTES y DESPUÉS (captura, curl o reporte) en 09-Evidencias/<ID>. El informe se arma con eso.
A40: • | B40: Ninguna corrección de seguridad se mergea antes de que exista el escaneo «antes» (VULN-01).
A41: • | B41: Secretos y contraseñas: nunca en el chat ni en el repo; solo en la bóveda KeePassXC (PWM-01).
A42: • | B42: Nombres de entrega: ProyNombreGrupo-N.pdf y PresNombreGrupo-N.pdf (N = 1 el martes, 2 el jueves).
A43: • | B43: Defensa individual = 60 % de la nota: cada uno estudia también lo que hicieron los demás (hoja «Defensa»).
A45: Riesgos del sprint
A46: Riesgo | B46: Mitigación | C46: Responsable
A47: Regla del LMS: el PDF pide subir los documentos dos días antes de la defensa. Si el martes es la defensa, la entrega 1 vencía el domingo 11. | B47: C-02 lo confirma el sábado a las 12:00. Si aplica, ENT-03 pasa al domingo con una versión preliminar. | H47: Alan
A48: La integración con Keycloak se complica. | B48: Spike con timebox de 4 h y go/no-go el sábado 18:00. Plan B: IAM-07. | H48: Nicole
A49: Cruce con el Sprint 3 de DoggyCredit (mismo equipo, termina el martes 13). | B49: Acordar en el kickoff cuántas horas se dedican a cada proyecto. | H49: Nicole
A50: Alan y Favian todavía no están en Linear. | B50: Nicole les envía la invitación al equipo Los 6 Siniestros; sus tareas ya llevan su nombre en el título. | H50: Nicole
A51: Sobrecarga el lunes (code freeze + redacción + PDF). | B51: Las secciones se redactan en borrador apenas termina cada tarea; el lunes solo se ajustan. | H51: Todos
A53: Hojas de este archivo
A54: Tareas | B54: Las 73 tareas con responsable, fecha y hora límite, dependencias, criterio de aceptación y evidencia. Editar solo Estado y Notas.
A55: Carga | B55: Horas por persona y día, y avance (calculado).
A56: Cronograma | B56: Qué vence en cada bloque del día, por persona, con los hitos del equipo.
A57: Dependencias | B57: Ruta crítica y cadenas de dependencia por frente.
A58: Cobertura PDF | B58: Cada exigencia del PDF de la docente y cada documento extra pedido → tareas que lo cubren.
A59: Documentos | B59: Catálogo de todos los documentos a producir (políticas, procedimientos, matrices…) con estado automático.
A60: Decisiones | B60: Lo que se decide en el kickoff (propuestas ya cargadas; completar la columna amarilla).
A61: Defensa | B61: Banco de preguntas para preparar la defensa individual (60 % de la nota).

Sheet Tareas
A1: Backlog del sprint — tareas, responsables y dependencias
A2: Fuente única. Editar solo la columna Estado (desplegable) y Notas. El resto se mantiene sincronizado con Linear.
A3: Leyenda: celdas amarillas = editables. Prioridad: Urgente = ruta crítica del sábado · Alta = necesaria para el martes · Media = martes si alcanza · Baja = jueves / opcional / plan B.
A4: ID | B4: Linear | C4: Tarea | D4: Responsable | E4: Apoyo | F4: Frente | G4: Tipo | H4: Sección del informe | I4: Día | J4: Fecha límite | K4: Hora límite | L4: Prioridad | M4: Horas est. | N4: Depende de | O4: Bloquea a | P4: Qué hacer | Q4: Criterio de aceptación | R4: Evidencia / entregable | S4: Estado | T4: Notas / bloqueos
A5: C-01 | B5: SINS-1 | C5: Kickoff y decisiones de diseño | D5: Nicole | E5: Todos | F5: Coordinación | G5: Coordinación | H5: — | I5: Sáb 10 | J5: 46305 | K5: 10:00 | L5: Urgente | M5: 1 | N5: — | O5: IAM-01, IAM-04, PWM-01, RBAC-01, GRC-00, GRC-01, MOD15-01, PO-03, INF-00 | P5: Reunión de arranque (9:00–10:00, todos). Decidir y registrar en la hoja «Decisiones» del Excel: (1) parámetros de la política de contraseñas; (2) formato del User ID; (3) tema del módulo 15; (4) Keycloak como gestor de identidades y KeePassXC como gestor de contraseñas; (5) nombre del grupo para los archivos; (6) carpeta compartida y convención de ramas; (7) horario de dailies; (8) prioridad frente al Sprint 3 de DoggyCredit. Confirmar que Alan y Favian ya aceptaron la invitación a Linear (equipo Los 6 Siniestros), al repo y a la carpeta compartida. | Q5: Hoja Decisiones completa y comunicada. Las 6 personas tienen acceso a Linear, al repo y a la carpeta compartida. | R5: Hoja «Decisiones» del Excel completa | S5: Pendiente
A6: C-02 | B6: SINS-2 | C6: Confirmar con la docente las reglas de entrega | D6: Alan | E6: Nicole | F6: Coordinación | G6: Coordinación | H6: Entregables | I6: Sáb 10 | J6: 46305 | K6: 12:00 | L6: Urgente | M6: 0.5 | N6: — | O6: ENT-02 | P6: Confirmar con la Mgr. Ing. Lourdes Peredo: (a) si el martes 13 es la defensa o un avance. El PDF exige subir los documentos al LMS dos días antes de la defensa; si aplica, la entrega 1 vence el domingo 11. (b) Formato del póster. (c) Versión de ISO 27002 esperada. (d) Qué se exige en la entrega 1 y qué en la entrega 2. | Q6: Respuestas registradas en «Decisiones». Si aplica la regla de los 2 días, ENT-03 se re-planifica al domingo 11 (23:59). | R6: Mensaje o captura con la respuesta de la docente | S6: Pendiente
A7: C-03 | B7: SINS-66 | C7: Code freeze, merge a develop y despliegue estable | D7: Nicole | E7: Todos los devs | F7: Coordinación | G7: Coordinación | H7: 8, demo | I7: Lun 12 | J7: 46307 | K7: 18:00 | L7: Urgente | M7: 2 | N7: IAM-06, RBAC-05, LOG-04, HARD-04, CRY-02, DEP-01 | O7: C-04 | P7: Congelar el código a las 18:00. Mergear a develop las ramas seg/* revisadas, crear el tag v-seg-1 y redesplegar. Smoke test de la demo completa con un usuario por rol. Generar SHA256SUMS de los artefactos (script de CRY-03). | Q7: La demo completa funciona en el enlace público y no queda ningún PR de seguridad abierto. | R7: Tag v-seg-1, checklist de smoke test, SHA256SUMS | S7: En curso | T7: [Corregido 24/10] CI/CD del backend reactivado por Alvaro (push a main despliega) y del frontend reactivado. En producción, GATEWAY_ALLOWED_ORIGINS debe incluir https://medicalsys.los5furiosos.cloud o el login falla por CORS. [Revisión de código 23/10] Merge de todas las ramas a develop y main hecho (4d0f660), con pruebas unitarias y e2e en verde. Falta: tag v-seg-1, SHA256SUMS de la entrega y despliegue en el enlace público.
A8: C-04 | B8: SINS-69 | C8: Ensayo de defensa individual (60 % de la nota) | D8: Nicole | E8: Todos | F8: Coordinación | G8: Coordinación | H8: Defensa | I8: Mar 13 | J8: 46308 | K8: 07:30 | L8: Urgente | M8: 2 | N8: ENT-01, C-03 | O8: — | P8: Lunes 21:30 y martes 7:00. Cada integrante explica el sistema COMPLETO, no solo su parte. Ronda de preguntas cruzadas con el banco de la hoja «Defensa» (por qué Argon2id, mediación completa, hash vs HMAC, KRIs, ISO 2013 vs 2022…). Guion de demo con tiempos. | Q8: Las 6 personas responden al menos 10 preguntas del banco sin apoyo y la demo dura menos de 8 minutos. | R8: Guion de demo con responsables y tiempos | S8: Pendiente
A9: IAM-01 | B9: SINS-10 | C9: Spike Keycloak + go/no-go (timebox 4 h) | D9: Nicole | E9: Juanjo | F9: Identidad y contraseñas | G9: Código | H9: 9.1, 9.3 | I9: Sáb 10 | J9: 46305 | K9: 18:00 | L9: Urgente | M9: 4 | N9: C-01 | O9: IAM-02, IAM-04, IAM-07, PWM-01 | P9: Agregar Keycloak (imagen quay.io/keycloak/keycloak con versión fija) a compose.yaml, con base «keycloak» en el Postgres existente. Crear el realm «medicalsys», exportarlo a infra/keycloak/realm-medicalsys.json e importarlo al arrancar. Crear el cliente confidencial «ms-identidad» con Direct Access Grants y service account con el rol manage-users (realm-management). Probar el token endpoint con un usuario de prueba. Go/no-go a las 18:00: si falla, se activa IAM-07 (plan B). | Q9: docker compose up keycloak arranca con el realm importado, se obtiene un token de un usuario de prueba y la decisión go/no-go queda registrada en Linear. | R9: Captura de la consola de Keycloak y respuesta del token endpoint | S9: Hecha | T9: [Revisión de código 23/10] Keycloak 26.7.5 con el realm medicalsys importado; smoke-token.sh en verde. Decisión GO.
A10: IAM-02 | B10: SINS-41 | C10: Política de contraseñas y bloqueo al 3er intento en Keycloak | D10: Nicole | E10: Favian | F10: Identidad y contraseñas | G10: Código | H10: 9.3 | I10: Sáb 10 | J10: 46305 | K10: 22:00 | L10: Urgente | M10: 2 | N10: IAM-01, PO-03 | O10: IAM-03 | P10: Password policy del realm (con los valores de PO-03): length(12), maxLength(64), upperCase(1), lowerCase(1), digits(1), specialChars(1), notUsername, notEmail, passwordHistory(5), forceExpiredPasswordChange(90) y hashAlgorithm(argon2). Brute force detection con failureFactor=3 y permanentLockout=true (desbloqueo solo por un administrador). Re-exportar el realm. | Q10: Hay una captura por cada regla rechazando una contraseña inválida, 3 intentos fallidos bloquean la cuenta y la configuración está versionada en el repo. | R10: Capturas de cada regla y realm-medicalsys.json actualizado | S10: Hecha | T10: [Revisión de código 23/10] policy-check.sh en verde: 9 reglas, histórico de 5, Argon2id y bloqueo permanente al 3er intento. Realm versionado en infra/keycloak.
A11: IAM-03 | B11: SINS-51 | C11: Login de MedicalSys delegado a Keycloak | D11: Nicole | E11: Alvaro | F11: Identidad y contraseñas | G11: Código | H11: 9.3 | I11: Dom 11 | J11: 46306 | K11: 17:00 | L11: Urgente | M11: 5 | N11: IAM-02 | O11: IAM-05, IAM-08, DEP-01 | P11: AuthService.login valida las credenciales contra el token endpoint de Keycloak (cliente confidencial) y mapea las respuestas: credenciales inválidas → 401 genérico, cuenta bloqueada → 423, «Account is not fully set up» o contraseña vencida → 403 con PASSWORD_CHANGE_REQUIRED. Si el login es válido, emite el JWT propio de MedicalSys con roles y permisos; el contrato de /auth/login no cambia y el frontend no se toca. Migrar los usuarios demo a Keycloak; password_hash local deja de usarse. | Q11: Los 4 casos (ok, inválida, bloqueada, vencida) se demuestran con curl, los tests de AuthService pasan y el frontend sigue iniciando sesión. | R11: Colección curl/Postman y PR mergeado | S11: Hecha | T11: [Revisión de código 23/10] Login delegado a Keycloak: 200, 401 genérico, 423 bloqueada y 403 PASSWORD_CHANGE_REQUIRED verificados (login-keycloak.sh y e2e.sh). Tests de AuthService.
A12: IAM-04 | B12: SINS-22 | C12: ABM de usuarios sincronizado con Keycloak + User ID estándar | D12: Nicole | E12: Franco | F12: Identidad y contraseñas | G12: Código | H12: 9.1 | I12: Dom 11 | J12: 46306 | K12: 13:00 | L12: Alta | M12: 5 | N12: IAM-01, C-01 | O12: IAM-05, IAM-06, LOG-02, PR-01 | P12: Migración nueva en ms-identidad: columna user_code única e inmutable con el formato acordado en C-01 (propuesta MS-26-00001), generada por secuencia y nunca reutilizada. El alta crea el usuario en Keycloak (Admin REST API) con contraseña temporal y la acción requerida UPDATE_PASSWORD. La baja deshabilita, nunca borra, para conservar la trazabilidad. La modificación sincroniza nombre, correo y estado. | Q12: Alta, baja y modificación se reflejan en Keycloak y en MedicalSys, el User ID respeta el formato y la validación está cubierta por tests. | R12: Capturas de alta/baja/modificación y PR | S12: Hecha | T12: [Revisión de código 23/10] Alta, modificación y baja sincronizadas con Keycloak (la baja deshabilita, no borra). User ID MS-AA-NNNNN (migración V7) con tests.
A13: IAM-05 | B13: SINS-55 | C13: Desbloqueo, reinicio y cambio de contraseña | D13: Nicole | E13: — | F13: Identidad y contraseñas | G13: Código | H13: 9.3 | I13: Dom 11 | J13: 46306 | K13: 22:00 | L13: Alta | M13: 3 | N13: IAM-03, IAM-04 | O13: IAM-06, LOG-02, PR-02, INF-02 | P13: POST /api/v1/identity/users/{id}/unlock (permiso identity.user.unlock): limpia el bloqueo por fuerza bruta en Keycloak. POST /users/{id}/reset-password (identity.user.reset): contraseña temporal y cambio obligatorio. /auth/change-password resuelve también el caso de contraseña vencida; Keycloak valida el historial y la complejidad. | Q13: Demo completa: 3 intentos bloquean → se desbloquea desde la app → reinicio → cambio forzado → reutilizar una contraseña anterior es rechazado. | R13: Video corto o secuencia de capturas | S13: Hecha | T13: [Revisión de código 23/10] Bloqueo al 3er intento → desbloqueo → reinicio con temporal → cambio forzado → reutilizar anterior rechazado (desbloqueo-reinicio.sh).
A14: IAM-06 | B14: SINS-59 | C14: Pantallas de gestión de usuarios (frontend) | D14: Nicole | E14: Franco | F14: Identidad y contraseñas | G14: Código | H14: 9.1 | I14: Lun 12 | J14: 46307 | K14: 14:00 | L14: Alta | M14: 4 | N14: IAM-04, IAM-05 | O14: C-03, INF-03 | P14: Lista y búsqueda, alta, edición, baja, botones Desbloquear y Reiniciar contraseña, columnas User ID y estado. Mensajes claros cuando una contraseña no cumple la política (principio de menos asombro). | Q14: La demo funciona de punta a punta desde el navegador, sin tocar la base de datos ni la consola de Keycloak. | R14: Capturas de cada pantalla | S14: En revisión | T14: [Frontend 24/10] Integrada en main/develop del frontend (sins-59). Verificado en el navegador contra el backend: lista con User ID y estado de las 28 cuentas; los botones de alta, edición, baja, desbloqueo y reinicio llaman a los endpoints correctos; 103 tests del frontend en verde. Falta recorrer la demo completa en vivo (alta → temporal → desbloqueo → reinicio).
A15: IAM-07 | B15: SINS-23 | C15: [Plan B] Políticas de contraseña nativas en ms-identidad | D15: Nicole | E15: — | F15: Identidad y contraseñas | G15: Código | H15: 9.3 | I15: Dom 11 | J15: 46306 | K15: 18:00 | L15: Baja | M15: 6 | N15: IAM-01 | O15: — | P15: SOLO si IAM-01 da no-go. Tabla password_history con las últimas 5 contraseñas en Argon2id, password_changed_at con expiración a 90 días, max-failed-attempts=3 sin desbloqueo automático, endpoints de desbloqueo y reinicio y validador de complejidad. Si IAM-01 da go, cancelar esta tarea. | Q15: Cumple los mismos criterios que IAM-02 e IAM-05. | R15: Igual que IAM-02/IAM-05 | S15: Cancelada | T15: [Revisión de código 23/10] IAM-01 dio GO: el plan B no se activa.
A16: IAM-08 | B16: SINS-56 | C16: [Opcional jueves] Passkeys / WebAuthn para administradores | D16: Nicole | E16: — | F16: Identidad y contraseñas | G16: Código | H16: 9.3 | I16: Jue 15 | J16: 46310 | K16: 18:00 | L16: Baja | M16: 3 | N16: IAM-03 | O16: — | P16: Habilitar WebAuthn (passkeys) como inicio sin contraseña o segundo factor en Keycloak para PLATFORM_ADMIN y ADMINISTRATOR. Demostrar el registro y el inicio de sesión con passkey. | Q16: Un administrador inicia sesión con passkey y hay capturas del flujo. | R16: Capturas | S16: Pendiente | T16: [Revisión de código 23/10] Opcional. El realm no tiene WebAuthn/passkeys configurado.
A17: PWM-01 | B17: SINS-24 | C17: Gestor de contraseñas para resguardo (KeePassXC) y rotación de secretos | D17: Favian | E17: Nicole | F17: Identidad y contraseñas | G17: Documento GRC | H17: 9.3 | I17: Dom 11 | J17: 46306 | K17: 17:00 | L17: Alta | M17: 3 | N17: C-01, IAM-01 | O17: PR-08 | P17: Crear la base KeePassXC del equipo: cifrado AES-256 o ChaCha20, KDF Argon2id, contraseña maestra fuerte y archivo llave. Guardar ahí el admin de Keycloak, el platform admin, Aiven, MinIO, JWT_SECRET, CRYPTO_SERVICE_SHARED_SECRET, DEMO_MASTER_KEY, los tokens de Meta y los usuarios de prueba por rol. Generar secretos nuevos con el generador del gestor para reemplazar los valores de ejemplo del .env. | Q17: La bóveda se compartió por un canal seguro, hay capturas de su configuración (cifrado, KDF, generador) y no hay secretos en el chat ni en el repo. | R17: Capturas de la configuración de KeePassXC (sin valores) | S17: Pendiente
A18: RBAC-01 | B18: SINS-11 | C18: Catálogo granular de permisos por funcionalidad | D18: Franco | E18: — | F18: Roles y autorización | G18: Código | H18: 9.2 | I18: Sáb 10 | J18: 46305 | K18: 13:00 | L18: Urgente | M18: 3 | N18: C-01 | O18: RBAC-02, RBAC-03, RBAC-06, PO-02 | P18: Inventariar todas las funcionalidades (endpoints) de cada microservicio y definir permisos con el formato módulo.recurso.acción (clinical.encounter.sign, scheduling.appointment.cancel, notifications.whatsapp.send, audit.log.read, identity.user.unlock, identity.role.manage…). Crear una migración nueva en ms-identidad con los permisos y su asignación inicial a roles. Este catálogo es la fuente de la matriz de accesos (RBAC-06). | Q18: La migración está aplicada, GET /permissions devuelve el catálogo completo y cada endpoint del sistema tiene un permiso. | R18: Hoja de endpoints→permiso (borrador de la matriz) | S18: Hecha | T18: [Revisión de código 23/10] GET /api/v1/identity/permissions devuelve 169 permisos; los 252 endpoints coinciden con la matriz (scripts/ci/check_permissions.py).
A19: RBAC-02 | B19: SINS-25 | C19: API de gestión de roles (alta, baja y edición de permisos) | D19: Franco | E19: — | F19: Roles y autorización | G19: Código | H19: 9.2 | I19: Sáb 10 | J19: 46305 | K19: 20:00 | L19: Urgente | M19: 5 | N19: RBAC-01 | O19: RBAC-05, LOG-02, PR-03 | P19: Endpoints POST /roles, PATCH /roles/{code}, DELETE /roles/{code} (desactiva) y PUT /roles/{code}/permissions, protegidos con identity.role.manage. Segregación de funciones: nadie modifica sus propios roles ni permisos, y se pueden configurar pares de roles incompatibles. | Q19: Se crea un rol nuevo, se le asignan permisos y se le asigna a un usuario desde la API; tras volver a iniciar sesión, el usuario tiene acceso sin tocar código ni la BD. | R19: Colección Postman y PR | S19: Hecha | T19: [Actualizado 24/10, ISO-01] Desde la migración V9 de Alvaro, la gestión de roles y permisos es del OSI (ya no de PLATFORM_ADMIN). e2e.sh recorre el criterio con la cuenta OSI: rol nuevo → permiso → cuenta → nivel MAC → acceso, y el 403 donde corresponde. [Corregido 24/10] RoleManagementServiceTest (7 tests). La cuenta PLATFORM_ADMIN se activa por ENV_FILE (plantilla en docs/despliegue-vps.md). e2e.sh recorre el criterio completo: rol nuevo → permisos → usuario → acceso permitido y 403 donde corresponde. [Revisión de código 23/10] API de roles implementada (crear, editar, desactivar, permisos, roles asignables, incompatibilidades). Falta: tests automatizados (solo hay colección Postman) y una cuenta PLATFORM_ADMIN para la demo: solo ese rol tiene identity.role.manage y no existe por defecto (PLATFORM_ADMIN_SEED_ENABLED=false).
A20: RBAC-03 | B20: SINS-26 | C20: Autorización por permisos en todos los servicios | D20: Franco | E20: Juanjo | F20: Roles y autorización | G20: Código | H20: 9.2, 10 | I20: Dom 11 | J20: 46306 | K20: 16:00 | L20: Urgente | M20: 6 | N20: RBAC-01 | O20: RBAC-04, LOG-04 | P20: El gateway propaga X-Permissions desde el claim permissions; agregarlo a TRUSTED_HEADERS para que el cliente no pueda inyectarlo. Crear la anotación @RequiresPermission con su interceptor en cada servicio (mismo patrón que RoleAuthorizationInterceptor) y reemplazar los @RequiresRole con roles fijos en el código. | Q20: Cambiar los permisos de un rol desde la API cambia el acceso real en historial, pacientes y facturación sin redesplegar, y hay tests del interceptor. | R20: Antes/después: rol sin permiso → 403 | S20: Hecha | T20: [Revisión de código 23/10] No queda ningún @RequiresRole; el gateway propaga X-Permissions desde el JWT y descarta los que envía el cliente. Tests del interceptor.
A21: RBAC-04 | B21: SINS-42 | C21: Denegar por defecto y cubrir los servicios sin control | D21: Franco | E21: — | F21: Roles y autorización | G21: Código | H21: 10, 11 | I21: Lun 12 | J21: 46307 | K21: 11:00 | L21: Alta | M21: 5 | N21: RBAC-03 | O21: VULN-02, INF-02, INF-05 | P21: El interceptor rechaza con 403 todo endpoint sin @RequiresPermission, salvo los marcados explícitamente con @PublicEndpoint. Proteger ms-agenda (30 endpoints), ms-profesionales, ms-notificaciones (incluida la consola manual de WhatsApp) y ms-catalogos. Script o colección de pruebas: 401 sin token, 403 con un rol sin permiso, 200 con el permiso. | Q21: El script pasa y ningún endpoint de negocio queda sin anotación (comprobado con grep). | R21: Salida del script de pruebas de autorización | S21: Hecha | T21: [Revisión de código 23/10] Denegar por defecto: todos los endpoints declaran su control (check_permissions.py); sin token responde 401.
A22: RBAC-05 | B22: SINS-43 | C22: Pantallas de roles y matriz de accesos editable (frontend) | D22: Franco | E22: Nicole | F22: Roles y autorización | G22: Código | H22: 9.2 | I22: Lun 12 | J22: 46307 | K22: 16:00 | L22: Alta | M22: 5 | N22: RBAC-02 | O22: C-03, INF-04 | P22: CRUD de roles, matriz rol × permiso con checkboxes agrupada por módulo y asignación de roles a usuarios. La matriz se puede exportar a CSV/Excel desde la app. | Q22: Demo: quitar un permiso en la matriz hace que el usuario reciba 403 en esa funcionalidad tras volver a iniciar sesión. | R22: Capturas y matriz exportada | S22: En revisión | T22: [Actualizado 24/10, ISO-01] La matriz se edita con la cuenta OSI (OSI_SEED_ENABLED en ENV_FILE). Falta en el frontend una pantalla para fijar el nivel MAC de una cuenta: hoy solo por API (PUT /users/{id}/clearance). [Corregido 24/10] Desbloqueada: con la cuenta PLATFORM_ADMIN la matriz se puede editar. Falta solo recorrer la demo en vivo desde la pantalla. [Frontend 24/10] Pantallas de roles y matriz (169 permisos × 6 roles) con exportación CSV/Excel, verificadas en el navegador. Para la demo de editar la matriz hace falta una cuenta PLATFORM_ADMIN (mismo bloqueo que RBAC-02): ADMINISTRATOR no tiene identity.role.manage.
A23: RBAC-06 | B23: SINS-27 | C23: Matriz de roles y accesos (plantilla Excel) | D23: Franco | E23: Alan | F23: Roles y autorización | G23: Documento GRC | H23: 9.2 | I23: Lun 12 | J23: 46307 | K23: 14:00 | L23: Alta | M23: 3 | N23: RBAC-01 | O23: INF-04, INF-09 | P23: Excel de roles × funcionalidades por módulo, con permisos C/R/U/D/Aprobar/Ejecutar, columnas de justificación (mínimo privilegio, segregación) y firma del responsable. Borrador el sábado a partir del seed actual; versión final el lunes, alineada con lo implementado. | Q23: Coincide 1:1 con la matriz exportada desde la app (RBAC-05) y va como anexo del informe. | R23: Matriz_Roles_Accesos.xlsx | S23: Pendiente
A24: VULN-01 | B24: SINS-3 | C24: Escaneo de vulnerabilidades de línea base (ANTES) | D24: Juanjo | E24: — | F24: Hardening y escaneo | G24: Código | H24: 13 | I24: Sáb 10 | J24: 46305 | K24: 14:00 | L24: Urgente | M24: 4 | N24: — | O24: HARD-01, HARD-02, HARD-03, HARD-04, PO-07, PR-04 | P24: Sobre el develop actual levantado en Docker: OWASP ZAP (baseline y, si hay OpenAPI, API scan) contra el gateway; Trivy sobre las imágenes medicalsys/*:local; Trivy fs u OWASP Dependency-Check sobre los pom.xml. Guardar los reportes en docs/seguridad/escaneos/antes/. NINGUNA corrección de seguridad se mergea antes de terminar este escaneo. | Q24: Los 3 reportes están guardados con fecha y hay un resumen de hallazgos por severidad en el comentario del issue. | R24: Reportes HTML/JSON de ZAP, Trivy y Dependency-Check | S24: Hecha | T24: [Revisión de código 23/10] Reportes Trivy (fs e imágenes) y ZAP del 12/10 en docs/seguridad/escaneos/antes/.
A25: HARD-01 | B25: SINS-12 | C25: Red interna y cierre de puertos (mediación completa, OWASP A01) | D25: Juanjo | E25: — | F25: Hardening y escaneo | G25: Código | H25: 10, 11 | I25: Sáb 10 | J25: 46305 | K25: 20:00 | L25: Urgente | M25: 3 | N25: VULN-01 | O25: HARD-05, VULN-02, DEP-01, INF-02, INF-05, INF-06 | P25: Crear la red medicalsys-interna en compose.yaml y quitar «ports:» de los 13 microservicios y de Postgres, Redis, Kafka y MinIO. Solo quedan expuestos el gateway y Keycloak (si hace falta). Hoy cualquiera puede hacer curl a :8088 con cabeceras X-Roles falsas y saltarse el gateway. Actualizar el README. | Q25: curl a localhost:8088 con X-Roles falso ya no responde y todo sigue funcionando a través del gateway (smoke test). | R25: Antes/después del curl directo | S25: Hecha | T25: [Revisión de código 23/10] Solo el gateway (8080) y Keycloak (18080) publican puerto; X-User-Id/X-Roles falsos sin token → 401 (e2e.sh).
A26: HARD-02 | B26: SINS-13 | C26: Revocación de sesión en el gateway (OWASP A07) | D26: Juanjo | E26: Nicole | F26: Hardening y escaneo | G26: Código | H26: 10, 11 | I26: Dom 11 | J26: 46306 | K26: 14:00 | L26: Alta | M26: 4 | N26: VULN-01 | O26: VULN-02, INF-06 | P26: El gateway comprueba que el jti del JWT siga activo en Redis (mismo SessionStore de ms-identidad) o lo consulta en un endpoint interno de identidad. Así el logout invalida el token en TODA la plataforma; hoy sigue valiendo hasta 1 h en los demás servicios. | Q26: Tras el logout, el mismo token recibe 401 en historial y pacientes. | R26: Antes/después con el mismo token | S26: Hecha | T26: [Revisión de código 23/10] Probado: tras el logout, el mismo token recibe 401 en pacientes, historial y facturación.
A27: HARD-03 | B27: SINS-14 | C27: Seguridad por defecto: webhook, CORS, usuarios demo (OWASP A05/A08) | D27: Juanjo | E27: — | F27: Hardening y escaneo | G27: Código | H27: 10, 11 | I27: Sáb 10 | J27: 46305 | K27: 22:00 | L27: Alta | M27: 2 | N27: VULN-01 | O27: VULN-02, INF-02, INF-05, INF-06 | P27: Webhook de WhatsApp: el servicio no arranca si el proveedor es meta y WHATSAPP_APP_SECRET está vacío, y rechaza las solicitudes sin firma (hoy se omite la verificación). CORS solo para los orígenes del frontend. IDENTITY_DEMO_USERS_ENABLED=false por defecto. /internal/v1/** de identidad deja de ser permitAll. Actuator con show-details: when-authorized. | Q27: Un payload de webhook sin firma recibe 401, un origen no permitido queda bloqueado y hay evidencias antes/después. | R27: Antes/después de cada punto | S27: Hecha | T27: [Corregido 24/10] La contraseña demo ya no está en el código del frontend: el botón de cuenta demo completa solo el correo. [Revisión de código 23/10] Webhook sin firma → 401; con meta y sin WHATSAPP_APP_SECRET no arranca; CORS por lista exacta (origen ajeno → 403); cuentas demo apagadas; /internal de identidad denyAll; actuator sin detalles. Ojo: el .env local de Nicole tiene GATEWAY_ALLOWED_ORIGINS=*. [Frontend 24/10] Observación: el frontend tiene DEMO_PASSWORD = 'Demo1234!' en login-page.ts, que viaja en el JavaScript público. Además ya no coincide con la contraseña demo por defecto del backend (SanGabriel.Demo26!).
A28: HARD-04 | B28: SINS-15 | C28: Corregir los hallazgos críticos y altos del escaneo | D28: Juanjo | E28: Alvaro | F28: Hardening y escaneo | G28: Código | H28: 13 | I28: Dom 11 | J28: 46306 | K28: 20:00 | L28: Alta | M28: 4 | N28: VULN-01 | O28: C-03, VULN-02 | P28: Actualizar las dependencias con CVE críticos o altos. Agregar cabeceras de seguridad en el gateway (HSTS, X-Content-Type-Options, CSP frame-ancestors, Referrer-Policy). Quitar banners y versiones expuestas. | Q28: Cada hallazgo crítico o alto queda corregido o tiene una justificación de riesgo aceptado. | R28: Lista hallazgo → PR | S28: Hecha | T28: [Corregido 24/10] Frontend: nginx con CSP (script-src 'self'), X-Frame-Options, nosniff, Referrer-Policy y Permissions-Policy, sin versión en Server; Caddy agrega HSTS. Verificado en el navegador: sin violaciones de CSP. [Revisión de código 23/10] Cabeceras HSTS, nosniff, X-Frame-Options, CSP y Referrer-Policy verificadas; re-escaneo del 12/10 con 0 críticas y 0 altas. [Frontend 24/10] Falta en el frontend: nginx sirve el HTML y el JS sin cabeceras de seguridad (CSP, X-Frame-Options, nosniff, Referrer-Policy, HSTS) y expone su versión (Server: nginx/1.27.5). Las dependencias del frontend quedaron en 0 vulnerabilidades (Angular 22.2.3).
A29: HARD-05 | B29: SINS-28 | C29: [Opcional jueves] Usuario de BD por microservicio (mínimo privilegio) | D29: Juanjo | E29: — | F29: Hardening y escaneo | G29: Código | H29: 10 | I29: Jue 15 | J29: 46310 | K29: 18:00 | L29: Baja | M29: 3 | N29: HARD-01 | O29: — | P29: En Aiven, crear un usuario MySQL por servicio con GRANT solo sobre su base (hoy los 13 comparten el mismo usuario). Actualizar compose.yaml y .env y guardar las credenciales en la bóveda. | Q29: ms-marketing no puede leer identity_db (captura del error de permisos). | R29: Captura del error de permisos | S29: Hecha | T29: [Revisión de código 23/10] Con MySQL local cada servicio tiene su usuario: marketing_user no puede leer identity_db (probado).
A30: VULN-02 | B30: SINS-52 | C30: Re-escaneo (DESPUÉS) y comparativa | D30: Juanjo | E30: — | F30: Hardening y escaneo | G30: Código | H30: 13 | I30: Lun 12 | J30: 46307 | K30: 17:00 | L30: Alta | M30: 3 | N30: HARD-01, HARD-02, HARD-03, HARD-04, RBAC-04 | O30: INF-08 | P30: Repetir las mismas herramientas con la misma configuración de VULN-01 sobre la versión corregida. Tabla comparativa: hallazgo, severidad, antes, después y PR de la corrección. Reportes en docs/seguridad/escaneos/despues/. | Q30: La tabla está lista para la sección 13 y muestra una reducción demostrable de hallazgos. | R30: Reportes «después» y tabla comparativa | S30: Hecha | T30: [Revisión de código 23/10] Comparativa en docs/seguridad/escaneos/despues/. Recomendado: re-escanear la versión final, porque Keycloak 26.7.5, IAM y LOG se integraron después del 12/10.
A31: DEP-01 | B31: SINS-57 | C31: Sistema ejecutable publicado (enlace de la rúbrica) | D31: Juanjo | E31: Nicole | F31: Hardening y escaneo | G31: Código | H31: Entregables | I31: Lun 12 | J31: 46307 | K31: 12:00 | L31: Alta | M31: 3 | N31: HARD-01, IAM-03 | O31: C-03 | P31: Túnel de Cloudflare existente hacia el gateway y el frontend (y Keycloak si se usa su consola), con HTTPS. Usuarios de prueba por rol documentados en la bóveda. Verificar el acceso desde una red externa (datos móviles). | Q31: El enlace público funciona y está anotado en el informe. | R31: URL pública y captura desde el móvil | S31: En curso | T31: [Revisión de código 23/10] El servicio cloudflared está listo en compose (perfil publico), pero no hay token configurado ni URL pública confirmada; el deploy al VPS está pausado.
A32: CRY-01 | B32: SINS-4 | C32: Inventario criptográfico y estándar de algoritmos | D32: Alvaro | E32: Nicole | F32: Criptografía e integridad | G32: Documento GRC | H32: 9.3, anexo | I32: Sáb 10 | J32: 46305 | K32: 14:00 | L32: Alta | M32: 3 | N32: — | O32: CRY-04, PO-05 | P32: Tabla con mecanismo, propósito, ubicación (servicio/archivo), algoritmo, longitud de clave, gestión de la clave y estado. Incluye: Argon2id (contraseñas), AES-256-GCM + HKDF-SHA256 por tenant (narrativa clínica, ms-criptografia), HMAC-SHA256 (webhook de Meta), SHA-256 (documentos, consentimientos, cadena de la bitácora, firma de encuentros), JWT HS256 (evaluar RS256), TLS (Aiven sslMode=REQUIRED, túnel HTTPS) y OTP con hash y sal. Algoritmos prohibidos: MD5, SHA-1, DES/3DES, RC4, ECB. | Q32: La tabla está revisada por Nicole y sirve de base a PO-05 y al anexo de criptografía. | R32: Inventario_Criptografico.xlsx | S32: Pendiente
A33: CRY-02 | B33: SINS-5 | C33: Verificación de integridad por hash en documentos (ms-documental) | D33: Alvaro | E33: — | F33: Criptografía e integridad | G33: Código | H33: 8, anexo | I33: Sáb 10 | J33: 46305 | K33: 19:00 | L33: Alta | M33: 4 | N33: — | O33: C-03, CRY-04, PR-05, INF-02 | P33: ms-documental ya guarda sha256_hash al subir un archivo. Agregar la verificación al descargar: recalcular y comparar; si no coincide, responder 409 INTEGRITY_MISMATCH y registrar un evento de auditoría. Nuevo endpoint GET /api/v1/documents/{id}/integrity (hash esperado vs calculado). Verificar también el PDF de los consentimientos firmados. | Q33: Demo: al alterar el objeto en MinIO, la descarga se bloquea y queda registrada. Hay tests. | R33: Antes/después de alterar el objeto | S33: Hecha | T33: [Revisión de código 23/10] La descarga se bloquea con 409 INTEGRITY_MISMATCH y evento de auditoría; GET /documents/{id}/integrity (permiso documents.document.read); cubre los consentimientos firmados. Tests.
A34: CRY-03 | B34: SINS-6 | C34: Checksums de artefactos y archivos (SHA256SUMS) | D34: Alvaro | E34: — | F34: Criptografía e integridad | G34: Código | H34: anexo | I34: Sáb 10 | J34: 46305 | K34: 21:00 | L34: Media | M34: 2 | N34: — | O34: CRY-04, PR-05 | P34: Script scripts/checksums.sh (y .ps1) que genera SHA256SUMS de los JAR, las imágenes, el export del realm y los PDF de entrega, y los verifica con sha256sum -c. Comparar con CRC32 y MD5 para explicar la diferencia entre checksum y hash criptográfico. Publicar SHA256SUMS junto a la entrega. | Q34: Al modificar 1 byte, la verificación falla (captura). | R34: SHA256SUMS y captura de la verificación fallida | S34: Hecha | T34: [Revisión de código 23/10] scripts/checksums.sh y checksums.ps1 con SHA-256 y comparación con CRC32 y MD5.
A35: CRY-04 | B35: SINS-16 | C35: Anexo y demostración de criptografía | D35: Alvaro | E35: — | F35: Criptografía e integridad | G35: Informe | H35: 9.3, anexo | I35: Lun 12 | J35: 46307 | K35: 15:00 | L35: Alta | M35: 3 | N35: CRY-01, CRY-02, CRY-03 | O35: INF-09 | P35: Guion de demo para la defensa: la nota clínica aparece cifrada en la BD (consulta SQL) y legible solo vía la app autorizada; contraseñas en Argon2id dentro de Keycloak; HMAC del webhook; hash de documentos; diferencias entre hash, HMAC, cifrado y firma. Redactar el anexo de criptografía y el párrafo de «protocolo de encriptación» de la sección 9.3. | Q35: El anexo está en el informe y la demo se ensayó en menos de 3 minutos. | R35: Anexo redactado | S35: Pendiente
A36: LOG-01 | B36: SINS-7 | C36: Cliente de auditoría en ms-identidad + eventos de autenticación | D36: Alvaro | E36: Nicole | F36: Logs de seguridad | G36: Código | H36: 12 | I36: Dom 11 | J36: 46306 | K36: 13:00 | L36: Alta | M36: 3 | N36: — | O36: LOG-02 | P36: Cliente HTTP hacia /internal/v1/audit-events de ms-auditoria (mismo contrato que usan pacientes e historial, tolerante a fallos). Eventos LOGIN_SUCCESS, LOGIN_FAILED, ACCOUNT_LOCKED y LOGOUT con actor, IP, user-agent, correlation id y resultado, sin contraseñas. Coordinar con Nicole porque IAM-03 cambia AuthService. | Q36: Los eventos aparecen en audit_db y la cadena de hash es válida. | R36: Consulta de audit_db o captura | S36: Hecha | T36: [Corregido 24/10] La IP guardada es la del usuario: el gateway la calcula (solo cree X-Forwarded-For de un proxy interno) y la pasa en X-Client-Ip, que descarta si la manda el cliente. Verificado en e2e.sh. [Revisión de código 23/10] LOGIN_SUCCESS, LOGIN_FAILED, ACCOUNT_LOCKED y LOGOUT llegan a audit_db; cadena de hash íntegra (155 eventos). Corregido el 23/10: los intentos fallidos y con correos inexistentes se perdían. [Frontend 24/10] Observación: la IP que se guarda es la del gateway (172.19.x.x), no la del usuario: AuditTrail usa request.getRemoteAddr() y nadie lee X-Forwarded-For.
A37: LOG-02 | B37: SINS-60 | C37: Eventos de seguridad de ABM, roles y contraseñas | D37: Alvaro | E37: — | F37: Logs de seguridad | G37: Código | H37: 12 | I37: Lun 12 | J37: 46307 | K37: 13:00 | L37: Alta | M37: 3 | N37: LOG-01, IAM-04, IAM-05, RBAC-02 | O37: LOG-04, PR-06, INF-02, INF-07 | P37: Eventos USER_CREATED/UPDATED/DISABLED, ROLE_CREATED/DISABLED, ROLE_ASSIGNED/REVOKED, ROLE_PERMISSIONS_CHANGED, ACCOUNT_UNLOCKED, PASSWORD_RESET, PASSWORD_CHANGED y ACCESS_DENIED (los 403 de los interceptores). | Q37: Cada acción de la demo deja su evento con actor y objetivo. | R37: Captura de la bitácora tras la demo | S37: Hecha | T37: [Corregido 24/10] Ahora también se auditan los roles (ROLE_CREATED/UPDATED/DISABLED/PERMISSIONS_CHANGED/ASSIGNABLE_ROLES_CHANGED/INCOMPATIBILITY_*) y los 403 de todos los servicios, que registra el gateway como ACCESS_DENIED. Verificado en e2e.sh. [Revisión de código 23/10] Verificado en la bitácora: USER_CREATED/UPDATED/DISABLED, ACCOUNT_LOCKED/UNLOCKED, PASSWORD_RESET/CHANGED. Implementado sin prueba en vivo: ROLE_ASSIGNED/REVOKED y ACCESS_DENIED de identidad. Falta: ROLE_CREATED/DISABLED/PERMISSIONS_CHANGED (RoleManagementService no audita) y ACCESS_DENIED en los interceptores de los demás servicios.
A38: LOG-03 | B38: SINS-8 | C38: Logs de aplicación seguros (OWASP A09) | D38: Alvaro | E38: Juanjo | F38: Logs de seguridad | G38: Código | H38: 12 | I38: Dom 11 | J38: 46306 | K38: 16:00 | L38: Media | M38: 2 | N38: — | O38: INF-07 | P38: Formato estructurado con correlation id en todos los servicios y niveles coherentes. Revisar que no se registren contraseñas, tokens, OTP ni datos clínicos, y que las excepciones no devuelvan detalles internos al cliente. Documentar la retención (ya configurada en compose: 10 MB × 3 archivos). | Q38: Una muestra de logs de un flujo completo no contiene datos sensibles y la lista de correcciones está en el PR. | R38: Muestra de logs anonimizada | S38: Hecha | T38: [Corregido 24/10] ms-gateway con logback estructurado y correlation id en el MDC: los 14 servicios con el mismo formato. [Revisión de código 23/10] Logback estructurado con correlation id en 13 de 14 servicios: falta ms-gateway. Una muestra de logs del flujo completo no contiene tokens ni contraseñas.
A39: LOG-04 | B39: SINS-62 | C39: Consulta de logs de seguridad en la app | D39: Alvaro | E39: — | F39: Logs de seguridad | G39: Código | H39: 12 | I39: Lun 12 | J39: 46307 | K39: 17:00 | L39: Media | M39: 3 | N39: LOG-02, RBAC-03 | O39: C-03, INF-07 | P39: Pantalla de bitácora (usuario, acción, fecha, resultado, IP) con filtros y botón «verificar integridad», que usa el endpoint existente de ms-auditoria. Protegida con audit.log.read (solo AUDITOR y ADMIN). | Q39: Demo filtrando los intentos fallidos y los bloqueos del día. | R39: Captura de la pantalla | S39: Hecha | T39: [Frontend 24/10] Pantalla de bitácora verificada en el navegador: cadena íntegra (158 eventos), resumen, filtros por área/resultado/acción, columna IP, exportación CSV y botón Verificar integridad. Solo ve la ruta quien tiene el permiso.
A40: GRC-00 | B40: SINS-17 | C40: Plantilla de políticas y procedimientos + carpeta compartida | D40: Favian | E40: — | F40: Documentación GRC | G40: Documento GRC | H40: Anexos | I40: Sáb 10 | J40: 46305 | K40: 11:00 | L40: Urgente | M40: 1 | N40: C-01 | O40: GRC-02, PO-01, PO-02, PO-03, PO-04, PO-05, PO-06, PO-07, PR-01, PR-02, PR-03, PR-04, PR-05, PR-06, PR-07, PR-08 | P40: Plantilla con encabezado (código PO-xx/PR-xx, versión, fecha, clasificación del documento), objetivo, alcance, referencias (ISO/IEC 27001 y 27002, normativa nacional aplicable), roles y responsabilidades, definiciones, lineamientos o pasos, cumplimiento y sanciones, revisión, control de cambios y aprobación. Los procedimientos llevan además diagrama de flujo, entradas, salidas y registros. Crear la estructura de carpetas: 01-Informe, 02-Políticas, 03-Procedimientos, 04-Matrices, 05-ISO27002, 06-Brechas, 07-Riesgos, 08-Escaneos, 09-Evidencias, 10-Presentación-Póster. | Q40: La plantilla está publicada antes de las 11:00 y todos la usan. | R40: Plantilla_Politica.docx, Plantilla_Procedimiento.docx | S40: Pendiente
A41: GRC-01 | B41: SINS-18 | C41: Inventario de activos de información | D41: Favian | E41: Alan | F41: Documentación GRC | G41: Documento GRC | H41: 14, 15, anexo | I41: Sáb 10 | J41: 46305 | K41: 15:00 | L41: Urgente | M41: 3 | N41: C-01 | O41: GRC-02, RSK-01 | P41: Activos de MedicalSys. Información: historia clínica, datos de pacientes, consentimientos, facturas, credenciales, claves de cifrado, bitácora. Software: 13 microservicios, frontend, Keycloak. Servicios: Aiven MySQL, MinIO, Kafka, Redis, WhatsApp de Meta, Cloudflare. Personas y roles. Indicar el propietario y el custodio de cada uno. | Q41: Al menos 25 activos con propietario. Lo usan GRC-02 y RSK-01. | R41: Inventario_Activos.xlsx | S41: Pendiente
A42: GRC-02 | B42: SINS-29 | C42: Formulario de clasificación de la información | D42: Favian | E42: — | F42: Documentación GRC | G42: Documento GRC | H42: anexo | I42: Sáb 10 | J42: 46305 | K42: 20:00 | L42: Urgente | M42: 2 | N42: GRC-00, GRC-01 | O42: GRC-03, MOD15-01, PO-04, PR-07 | P42: Formulario por activo: identificación, propietario, tipo, valoración C/I/D (1–3) con criterios, requisitos legales, nivel resultante (Pública / Uso interno / Confidencial / Restringida) según una regla explícita (máximo de C/I/D) y controles de etiquetado y manejo. Versión llenable (Google Forms/MS Forms o Excel con validación). | Q42: El formulario está llenado para todos los activos del inventario. | R42: Formulario_Clasificacion + respuestas | S42: Pendiente
A43: GRC-03 | B43: SINS-44 | C43: Matriz de clasificación de la información | D43: Favian | E43: — | F43: Documentación GRC | G43: Documento GRC | H43: anexo | I43: Dom 11 | J43: 46306 | K43: 14:00 | L43: Alta | M43: 3 | N43: GRC-02 | O43: INF-09 | P43: Consolida los formularios: activo, propietario, C/I/D, nivel, etiqueta, ubicación y controles por nivel (cifrado en reposo y en tránsito, acceso, retención, eliminación segura). Hoja con las reglas de manejo por nivel. Debe ser coherente con la matriz de accesos y con la política de clasificación. | Q43: La matriz está completa y los activos «Restringida» (historia clínica) muestran los controles reales del sistema (AES-256-GCM, RBAC). | R43: Matriz_Clasificacion.xlsx | S43: Pendiente
A44: ISO-01 | B44: SINS-9 | C44: Tabla de controles ISO/IEC 27002:2022 | D44: Alan | E44: — | F44: Documentación GRC | G44: Documento GRC | H44: anexo, 15 | I44: Dom 11 | J44: 46306 | K44: 15:00 | L44: Alta | M44: 7 | N44: — | O44: ISO-02, ISO-03, INF-09 | P44: Los 93 controles en 4 temas (organizacionales 37, personas 8, físicos 14, tecnológicos 34). Por control: aplica (S/N) y justificación, estado en MedicalSys (implementado / parcial / no implementado), evidencia (archivo del repo, captura o política), responsable y acción. Priorizar los tecnológicos (8.x), control de acceso (5.15–5.18), criptografía (8.24), logs (8.15) y vulnerabilidades (8.8). | Q44: Las 93 filas están completas y hay un % de cumplimiento por tema (gráfico). | R44: ISO27002_2022_Controles.xlsx | S44: Pendiente
A45: ISO-02 | B45: SINS-19 | C45: Tabla de controles ISO/IEC 27002:2013 + mapeo 2013↔2022 | D45: Alan | E45: — | F45: Documentación GRC | G45: Documento GRC | H45: anexo | I45: Lun 12 | J45: 46307 | K45: 17:00 | L45: Media | M45: 4 | N45: ISO-01 | O45: — | P45: Los 114 controles en 14 dominios (A.5–A.18). Reutilizar la evaluación de la 2022 mediante la tabla de correspondencia del Anexo B de la 27002:2022. Hoja de mapeo y lista de los 11 controles nuevos de la 2022. | Q45: Las 114 filas y el mapeo están completos y las diferencias quedan destacadas. | R45: ISO27002_2013_Controles.xlsx | S45: Pendiente
A46: ISO-03 | B46: SINS-20 | C46: Fichas de evaluación de brechas | D46: Alan | E46: — | F46: Documentación GRC | G46: Documento GRC | H46: anexo, 8 | I46: Lun 12 | J46: 46307 | K46: 13:00 | L46: Alta | M46: 5 | N46: ISO-01 | O46: INF-09 | P46: Una ficha por control parcial o no implementado prioritario (mínimo 10–15): control, situación actual, situación deseada, brecha, riesgo asociado, acción correctiva, responsable, fecha, estado y evidencia de cierre (enlazar la tarea de Linear que lo corrige). | Q46: Las fichas de los controles corregidos en este sprint figuran como «cerrada» con su evidencia. | R46: Fichas_Brechas.docx/xlsx | S46: Pendiente
A47: RSK-01 | B47: SINS-30 | C47: Análisis de riesgos + 2 KRIs (sección 14) | D47: Alan | E47: Favian | F47: Documentación GRC | G47: Documento GRC | H47: 14 | I47: Dom 11 | J47: 46306 | K47: 19:00 | L47: Alta | M47: 4 | N47: GRC-01 | O47: INF-09 | P47: Metodología: probabilidad × impacto (1–5) y matriz de calor. R1: acceso no autorizado a historias clínicas (control de acceso roto, bypass del gateway). R2: compromiso de credenciales (fuerza bruta, contraseñas débiles, sesiones no revocadas). Por riesgo: amenaza, vulnerabilidad, impacto, nivel inherente, controles implementados en este sprint y riesgo residual. KRI-1: cuentas bloqueadas o intentos de login fallidos por día. KRI-2: accesos denegados (403) por día o vulnerabilidades críticas abiertas. Fuente de los datos: bitácora y escaneo. | Q47: La sección 14 está redactada y cada KRI tiene fórmula, umbrales verde/ámbar/rojo y fuente. | R47: Sección 14 + Matriz_Riesgos.xlsx | S47: Pendiente
A48: MOD15-01 | B48: SINS-45 | C48: Módulo de seguridad de información fuera del sistema (sección 15) | D48: Favian | E48: Alan | F48: Documentación GRC | G48: Código | H48: 15 | I48: Lun 12 | J48: 46307 | K48: 16:00 | L48: Alta | M48: 6 | N48: GRC-02, C-01 | O48: INF-09 | P48: Propuesta: herramienta automatizada de clasificación de activos. Formulario web o Forms → cálculo automático del nivel (C/I/D) → matriz de clasificación → dashboard (conteo por nivel, activos sin propietario). Alternativa si se decide así en el kickoff: evaluador ISO 27002 con % de cumplimiento por tema, sobre ISO-01. Implementar en Google Sheets + Apps Script o en una mini app web. | Q48: La demo funciona en vivo y la sección 15 está redactada con capturas. | R48: Enlace a la herramienta y capturas | S48: Pendiente | T48: [Revisión de código 23/10] Módulo fuera del sistema y de este repo: no se puede verificar aquí.
A49: PO-01 | B49: SINS-31 | C49: Política general de seguridad de la información | D49: Favian | E49: — | F49: Políticas | G49: Documento GRC | H49: anexo | I49: Dom 11 | J49: 46306 | K49: 12:00 | L49: Alta | M49: 2 | N49: GRC-00 | O49: — | P49: Compromiso de la dirección, objetivos de seguridad, alcance (MedicalSys y sus 13 microservicios), roles (propietario, custodio, usuario, oficial de seguridad), principios, marco de políticas específicas (PO-02 a PO-07) y revisión anual. | Q49: Usa la plantilla GRC-00 y fue revisada por otra persona. | R49: PO-01.docx | S49: Pendiente
A50: PO-02 | B50: SINS-32 | C50: Política de control de acceso | D50: Franco | E50: — | F50: Políticas | G50: Documento GRC | H50: 9.2, 10 | I50: Sáb 10 | J50: 46305 | K50: 21:00 | L50: Alta | M50: 1.5 | N50: GRC-00, RBAC-01 | O50: — | P50: RBAC por permisos granulares, mínimo privilegio, segregación de funciones, denegación por defecto, alta y baja de accesos, revisión periódica de accesos y cuentas privilegiadas. | Q50: Es coherente con RBAC-01 y RBAC-06. | R50: PO-02.docx | S50: Pendiente
A51: PO-03 | B51: SINS-33 | C51: Política de contraseñas y autenticación | D51: Favian | E51: Nicole | F51: Políticas | G51: Documento GRC | H51: 9.3 | I51: Sáb 10 | J51: 46305 | K51: 18:00 | L51: Alta | M51: 1.5 | N51: GRC-00, C-01 | O51: IAM-02, INF-03 | P51: Con los valores acordados en C-01: longitud mínima 12, complejidad (4 tipos de carácter), vida útil 90 días, historial de 5, bloqueo al 3er intento fallido, desbloqueo solo por un administrador, reinicio con contraseña temporal y cambio obligatorio, almacenamiento Argon2id y uso del gestor de contraseñas. Alimenta directamente la configuración de IAM-02. | Q51: Los valores son idénticos a los configurados en Keycloak (IAM-02). | R51: PO-03.docx | S51: Pendiente
A52: PO-04 | B52: SINS-46 | C52: Política de clasificación y manejo de la información | D52: Favian | E52: — | F52: Políticas | G52: Documento GRC | H52: anexo | I52: Dom 11 | J52: 46306 | K52: 20:00 | L52: Alta | M52: 1.5 | N52: GRC-00, GRC-02 | O52: — | P52: Los 4 niveles de clasificación, quién clasifica, etiquetado, manejo por nivel (almacenamiento, transmisión, impresión, retención, eliminación) y reclasificación. | Q52: Es coherente con GRC-02 y GRC-03. | R52: PO-04.docx | S52: Pendiente
A53: PO-05 | B53: SINS-34 | C53: Política criptográfica y de gestión de claves | D53: Alvaro | E53: — | F53: Políticas | G53: Documento GRC | H53: 9.3, anexo | I53: Dom 11 | J53: 46306 | K53: 18:00 | L53: Alta | M53: 1.5 | N53: GRC-00, CRY-01 | O53: — | P53: Algoritmos aprobados y prohibidos, longitudes mínimas, generación, almacenamiento, rotación y revocación de claves y secretos (DEK por tenant, master key → KMS a futuro), integridad por hash y uso de TLS. | Q53: Es coherente con CRY-01. | R53: PO-05.docx | S53: Pendiente
A54: PO-06 | B54: SINS-35 | C54: Política de registro y monitoreo (logs) | D54: Alvaro | E54: — | F54: Políticas | G54: Documento GRC | H54: 12 | I54: Dom 11 | J54: 46306 | K54: 20:00 | L54: Media | M54: 1.5 | N54: GRC-00 | O54: — | P54: Qué eventos se registran, qué datos NUNCA se registran, integridad (cadena de hash), retención, acceso a los logs (solo auditores) y revisión periódica. | Q54: Es coherente con LOG-01 a LOG-04. | R54: PO-06.docx | S54: Pendiente
A55: PO-07 | B55: SINS-36 | C55: Política de gestión de vulnerabilidades y desarrollo seguro | D55: Juanjo | E55: — | F55: Políticas | G55: Documento GRC | H55: 11, 13 | I55: Dom 11 | J55: 46306 | K55: 21:00 | L55: Media | M55: 1.5 | N55: GRC-00, VULN-01 | O55: — | P55: Escaneo periódico (ZAP, Trivy, Dependency-Check), plazos de corrección por severidad, revisión de código obligatoria, OWASP Top 10 como referencia y gestión de secretos. | Q55: Es coherente con PR-04. | R55: PO-07.docx | S55: Pendiente
A56: PR-01 | B56: SINS-47 | C56: Procedimiento de ABM de usuarios | D56: Nicole | E56: — | F56: Procedimientos | G56: Documento GRC | H56: 9.1 | I56: Lun 12 | J56: 46307 | K56: 15:00 | L56: Alta | M56: 1.5 | N56: GRC-00, IAM-04 | O56: — | P56: Paso a paso de alta, baja y modificación con capturas del sistema: solicitud y aprobación, generación del User ID, contraseña temporal y registro en la bitácora. | Q56: Las capturas son del sistema real. | R56: PR-01.docx | S56: Pendiente
A57: PR-02 | B57: SINS-61 | C57: Procedimiento de desbloqueo y reinicio de contraseña | D57: Nicole | E57: — | F57: Procedimientos | G57: Documento GRC | H57: 9.3 | I57: Lun 12 | J57: 46307 | K57: 16:00 | L57: Alta | M57: 1.5 | N57: GRC-00, IAM-05 | O57: — | P57: Verificación de identidad del solicitante, desbloqueo, reinicio con contraseña temporal, cambio obligatorio y registro en la bitácora, con capturas. | Q57: Las capturas son del sistema real. | R57: PR-02.docx | S57: Pendiente
A58: PR-03 | B58: SINS-48 | C58: Procedimiento de asignación/revocación de roles y revisión de accesos | D58: Franco | E58: — | F58: Procedimientos | G58: Documento GRC | H58: 9.2 | I58: Dom 11 | J58: 46306 | K58: 18:00 | L58: Alta | M58: 1.5 | N58: GRC-00, RBAC-02 | O58: — | P58: Solicitud, aprobación por el propietario, asignación desde la app, revocación al cambiar de puesto o en la baja, y revisión trimestral de accesos. | Q58: Es coherente con PO-02. | R58: PR-03.docx | S58: Pendiente
A59: PR-04 | B59: SINS-37 | C59: Procedimiento de gestión de vulnerabilidades | D59: Juanjo | E59: — | F59: Procedimientos | G59: Documento GRC | H59: 13 | I59: Dom 11 | J59: 46306 | K59: 22:00 | L59: Media | M59: 1.5 | N59: GRC-00, VULN-01 | O59: — | P59: Escaneo, triage por severidad (CVSS), asignación, corrección, re-escaneo de verificación y cierre, con los comandos exactos usados. | Q59: Es reproducible por otra persona. | R59: PR-04.docx | S59: Pendiente
A60: PR-05 | B60: SINS-38 | C60: Procedimiento de verificación de integridad de archivos (hash/checksum) | D60: Alvaro | E60: — | F60: Procedimientos | G60: Documento GRC | H60: anexo | I60: Dom 11 | J60: 46306 | K60: 21:00 | L60: Media | M60: 1.5 | N60: GRC-00, CRY-02, CRY-03 | O60: — | P60: Cómo generar y verificar SHA256SUMS (Linux y Windows: sha256sum / Get-FileHash), cómo verificar un documento en la app y qué hacer si no coincide. | Q60: Es reproducible por otra persona. | R60: PR-05.docx | S60: Pendiente
... A77: ENT-04 | B77: SINS-73 | C77: Entrega 2 (jueves): observaciones y pendientes | D77: Alan | E77: Todos | F77: Entregables | G77: Entregable | H77: Entregables | I77: Jue 15 | J77: 46310 | K77: 18:00 | L77: Media | M77: 3 | N77: ENT-03 | O77: — | P77: Incorporar las observaciones de la presentación del martes y las tareas opcionales que se completen (IAM-08, HARD-05, ENT-02). Regenerar ProyNombreGrupo-2.pdf y PresNombreGrupo-2.pdf y subirlos. | Q77: Los archivos -2 están subidos. | R77: Archivos -2.pdf | S77: Pendiente

Sheet Carga
A1: Carga de trabajo por persona y día
A2: Horas estimadas según el día de VENCIMIENTO (las tareas largas empiezan antes). Las tareas «Baja» (plan B / opcionales del jueves) van aparte.
A4: Persona | B4: Sáb 10 | C4: Dom 11 | D4: Lun 12 | E4: Mar 13 | F4: Jue 15 | G4: Total (sin Baja) | H4: Opcional / plan B | I4: Nº tareas | J4: Hechas | K4: % avance
A5: Nicole | B5: =SUMIFS(Tareas!$M$5:$M$77,Tareas!$D$5:$D$77,$A5,Tareas!$I$5:$I$77,B$4,Tareas!$L$5:$L$77,"<>Baja") | C5: =SUMIFS(Tareas!$M$5:$M$77,Tareas!$D$5:$D$77,$A5,Tareas!$I$5:$I$77,C$4,Tareas!$L$5:$L$77,"<>Baja") | D5: =SUMIFS(Tareas!$M$5:$M$77,Tareas!$D$5:$D$77,$A5,Tareas!$I$5:$I$77,D$4,Tareas!$L$5:$L$77,"<>Baja") | E5: =SUMIFS(Tareas!$M$5:$M$77,Tareas!$D$5:$D$77,$A5,Tareas!$I$5:$I$77,E$4,Tareas!$L$5:$L$77,"<>Baja") | F5: =SUMIFS(Tareas!$M$5:$M$77,Tareas!$D$5:$D$77,$A5,Tareas!$I$5:$I$77,F$4,Tareas!$L$5:$L$77,"<>Baja") | G5: =SUM(B5:F5) | H5: =SUMIFS(Tareas!$M$5:$M$77,Tareas!$D$5:$D$77,$A5,Tareas!$L$5:$L$77,"Baja") | I5: =COUNTIF(Tareas!$D$5:$D$77,$A5) | J5: =COUNTIFS(Tareas!$D$5:$D$77,$A5,Tareas!$S$5:$S$77,"Hecha") | K5: =IFERROR(J5/I5,0)
A6: Franco | B6: =SUMIFS(Tareas!$M$5:$M$77,Tareas!$D$5:$D$77,$A6,Tareas!$I$5:$I$77,B$4,Tareas!$L$5:$L$77,"<>Baja") | C6: =SUMIFS(Tareas!$M$5:$M$77,Tareas!$D$5:$D$77,$A6,Tareas!$I$5:$I$77,C$4,Tareas!$L$5:$L$77,"<>Baja") | D6: =SUMIFS(Tareas!$M$5:$M$77,Tareas!$D$5:$D$77,$A6,Tareas!$I$5:$I$77,D$4,Tareas!$L$5:$L$77,"<>Baja") | E6: =SUMIFS(Tareas!$M$5:$M$77,Tareas!$D$5:$D$77,$A6,Tareas!$I$5:$I$77,E$4,Tareas!$L$5:$L$77,"<>Baja") | F6: =SUMIFS(Tareas!$M$5:$M$77,Tareas!$D$5:$D$77,$A6,Tareas!$I$5:$I$77,F$4,Tareas!$L$5:$L$77,"<>Baja") | G6: =SUM(B6:F6) | H6: =SUMIFS(Tareas!$M$5:$M$77,Tareas!$D$5:$D$77,$A6,Tareas!$L$5:$L$77,"Baja") | I6: =COUNTIF(Tareas!$D$5:$D$77,$A6) | J6: =COUNTIFS(Tareas!$D$5:$D$77,$A6,Tareas!$S$5:$S$77,"Hecha") | K6: =IFERROR(J6/I6,0)
A7: Juanjo | B7: =SUMIFS(Tareas!$M$5:$M$77,Tareas!$D$5:$D$77,$A7,Tareas!$I$5:$I$77,B$4,Tareas!$L$5:$L$77,"<>Baja") | C7: =SUMIFS(Tareas!$M$5:$M$77,Tareas!$D$5:$D$77,$A7,Tareas!$I$5:$I$77,C$4,Tareas!$L$5:$L$77,"<>Baja") | D7: =SUMIFS(Tareas!$M$5:$M$77,Tareas!$D$5:$D$77,$A7,Tareas!$I$5:$I$77,D$4,Tareas!$L$5:$L$77,"<>Baja") | E7: =SUMIFS(Tareas!$M$5:$M$77,Tareas!$D$5:$D$77,$A7,Tareas!$I$5:$I$77,E$4,Tareas!$L$5:$L$77,"<>Baja") | F7: =SUMIFS(Tareas!$M$5:$M$77,Tareas!$D$5:$D$77,$A7,Tareas!$I$5:$I$77,F$4,Tareas!$L$5:$L$77,"<>Baja") | G7: =SUM(B7:F7) | H7: =SUMIFS(Tareas!$M$5:$M$77,Tareas!$D$5:$D$77,$A7,Tareas!$L$5:$L$77,"Baja") | I7: =COUNTIF(Tareas!$D$5:$D$77,$A7) | J7: =COUNTIFS(Tareas!$D$5:$D$77,$A7,Tareas!$S$5:$S$77,"Hecha") | K7: =IFERROR(J7/I7,0)
A8: Alvaro | B8: =SUMIFS(Tareas!$M$5:$M$77,Tareas!$D$5:$D$77,$A8,Tareas!$I$5:$I$77,B$4,Tareas!$L$5:$L$77,"<>Baja") | C8: =SUMIFS(Tareas!$M$5:$M$77,Tareas!$D$5:$D$77,$A8,Tareas!$I$5:$I$77,C$4,Tareas!$L$5:$L$77,"<>Baja") | D8: =SUMIFS(Tareas!$M$5:$M$77,Tareas!$D$5:$D$77,$A8,Tareas!$I$5:$I$77,D$4,Tareas!$L$5:$L$77,"<>Baja") | E8: =SUMIFS(Tareas!$M$5:$M$77,Tareas!$D$5:$D$77,$A8,Tareas!$I$5:$I$77,E$4,Tareas!$L$5:$L$77,"<>Baja") | F8: =SUMIFS(Tareas!$M$5:$M$77,Tareas!$D$5:$D$77,$A8,Tareas!$I$5:$I$77,F$4,Tareas!$L$5:$L$77,"<>Baja") | G8: =SUM(B8:F8) | H8: =SUMIFS(Tareas!$M$5:$M$77,Tareas!$D$5:$D$77,$A8,Tareas!$L$5:$L$77,"Baja") | I8: =COUNTIF(Tareas!$D$5:$D$77,$A8) | J8: =COUNTIFS(Tareas!$D$5:$D$77,$A8,Tareas!$S$5:$S$77,"Hecha") | K8: =IFERROR(J8/I8,0)
A9: Alan | B9: =SUMIFS(Tareas!$M$5:$M$77,Tareas!$D$5:$D$77,$A9,Tareas!$I$5:$I$77,B$4,Tareas!$L$5:$L$77,"<>Baja") | C9: =SUMIFS(Tareas!$M$5:$M$77,Tareas!$D$5:$D$77,$A9,Tareas!$I$5:$I$77,C$4,Tareas!$L$5:$L$77,"<>Baja") | D9: =SUMIFS(Tareas!$M$5:$M$77,Tareas!$D$5:$D$77,$A9,Tareas!$I$5:$I$77,D$4,Tareas!$L$5:$L$77,"<>Baja") | E9: =SUMIFS(Tareas!$M$5:$M$77,Tareas!$D$5:$D$77,$A9,Tareas!$I$5:$I$77,E$4,Tareas!$L$5:$L$77,"<>Baja") | F9: =SUMIFS(Tareas!$M$5:$M$77,Tareas!$D$5:$D$77,$A9,Tareas!$I$5:$I$77,F$4,Tareas!$L$5:$L$77,"<>Baja") | G9: =SUM(B9:F9) | H9: =SUMIFS(Tareas!$M$5:$M$77,Tareas!$D$5:$D$77,$A9,Tareas!$L$5:$L$77,"Baja") | I9: =COUNTIF(Tareas!$D$5:$D$77,$A9) | J9: =COUNTIFS(Tareas!$D$5:$D$77,$A9,Tareas!$S$5:$S$77,"Hecha") | K9: =IFERROR(J9/I9,0)
A10: Favian | B10: =SUMIFS(Tareas!$M$5:$M$77,Tareas!$D$5:$D$77,$A10,Tareas!$I$5:$I$77,B$4,Tareas!$L$5:$L$77,"<>Baja") | C10: =SUMIFS(Tareas!$M$5:$M$77,Tareas!$D$5:$D$77,$A10,Tareas!$I$5:$I$77,C$4,Tareas!$L$5:$L$77,"<>Baja") | D10: =SUMIFS(Tareas!$M$5:$M$77,Tareas!$D$5:$D$77,$A10,Tareas!$I$5:$I$77,D$4,Tareas!$L$5:$L$77,"<>Baja") | E10: =SUMIFS(Tareas!$M$5:$M$77,Tareas!$D$5:$D$77,$A10,Tareas!$I$5:$I$77,E$4,Tareas!$L$5:$L$77,"<>Baja") | F10: =SUMIFS(Tareas!$M$5:$M$77,Tareas!$D$5:$D$77,$A10,Tareas!$I$5:$I$77,F$4,Tareas!$L$5:$L$77,"<>Baja") | G10: =SUM(B10:F10) | H10: =SUMIFS(Tareas!$M$5:$M$77,Tareas!$D$5:$D$77,$A10,Tareas!$L$5:$L$77,"Baja") | I10: =COUNTIF(Tareas!$D$5:$D$77,$A10) | J10: =COUNTIFS(Tareas!$D$5:$D$77,$A10,Tareas!$S$5:$S$77,"Hecha") | K10: =IFERROR(J10/I10,0)
A11: Equipo | B11: =SUM(B5:B10) | C11: =SUM(C5:C10) | D11: =SUM(D5:D10) | E11: =SUM(E5:E10) | F11: =SUM(F5:F10) | G11: =SUM(G5:G10) | H11: =SUM(H5:H10) | I11: =SUM(I5:I10) | J11: =SUM(J5:J10) | K11: =IFERROR(J11/I11,0)
A13: Capacidad de referencia: ~11 h/día por persona (sáb, dom, lun). En rojo, más de 12 h vencen el mismo día: revisar en la daily si conviene mover algo.
A14: IAM-07 (plan B, 6 h) solo se ejecuta si Keycloak no pasa el go/no-go; si pasa, se cancela y esas horas se liberan.

Sheet Cronograma
A1: Cronograma — qué vence en cada bloque
A2: Mañana = hasta las 13:00 · Tarde = 13:01–18:00 · Noche = después de las 18:00. Cada celda lista las tareas que VENCEN en ese bloque.
A4: Persona | B4: Sáb 10 | C4: Sáb 10 | D4: Sáb 10 | E4: Dom 11 | F4: Dom 11 | G4: Dom 11 | H4: Lun 12 | I4: Lun 12 | J4: Lun 12 | K4: Mar 13 | L4: Jue 15
B5: Mañana | C5: Tarde | D5: Noche | E5: Mañana | F5: Tarde | G5: Noche | H5: Mañana | I5: Tarde | J5: Noche | K5: Mañana | L5: Día
A6: Nicole | B6: C-01 (10:00) | C6: IAM-01 (18:00) | D6: IAM-02 (22:00) | E6: IAM-04 (13:00) | F6: IAM-03 (17:00) IAM-07 (18:00) | G6: IAM-05 (22:00) | I6: C-03 (18:00) IAM-06 (14:00) PR-01 (15:00) PR-02 (16:00) | J6: INF-03 (19:00) | K6: C-04 (07:30) | L6: IAM-08 (18:00)
A7: Franco | B7: RBAC-01 (13:00) | D7: RBAC-02 (20:00) PO-02 (21:00) | F7: RBAC-03 (16:00) PR-03 (18:00) | H7: RBAC-04 (11:00) | I7: RBAC-05 (16:00) RBAC-06 (14:00) | J7: INF-04 (19:00) INF-05 (19:00)
A8: Juanjo | C8: VULN-01 (14:00) | D8: HARD-01 (20:00) HARD-03 (22:00) | F8: HARD-02 (14:00) | G8: HARD-04 (20:00) PO-07 (21:00) PR-04 (22:00) | H8: DEP-01 (12:00) | I8: VULN-02 (17:00) | J8: INF-06 (19:00) INF-08 (19:00) | L8: HARD-05 (18:00)
A9: Alvaro | C9: CRY-01 (14:00) | D9: CRY-02 (19:00) CRY-03 (21:00) | E9: LOG-01 (13:00) | F9: LOG-03 (16:00) PO-05 (18:00) | G9: PO-06 (20:00) PR-05 (21:00) | H9: LOG-02 (13:00) | I9: CRY-04 (15:00) LOG-04 (17:00) PR-06 (18:00) | J9: INF-07 (19:00)
A10: Alan | B10: C-02 (12:00) INF-00 (11:00) | D10: INF-01 (21:00) | F10: ISO-01 (15:00) | G10: RSK-01 (19:00) | H10: ISO-03 (13:00) | I10: ISO-02 (17:00) | J10: INF-02 (19:00) INF-09 (23:00) ENT-03 (23:59) | L10: ENT-04 (18:00)
A11: Favian | B11: GRC-00 (11:00) | C11: GRC-01 (15:00) PO-03 (18:00) | D11: GRC-02 (20:00) | E11: PO-01 (12:00) | F11: PWM-01 (17:00) GRC-03 (14:00) | G11: PO-04 (20:00) PR-07 (19:00) PR-08 (21:00) | I11: MOD15-01 (16:00) | J11: ENT-01 (23:00) | L11: ENT-02 (12:00)
A12: Hitos del equipo | B12: 09:00 Kickoff 11:00 Plantillas 12:00 Respuesta docente | C12: 14:00 Escaneo «antes» listo 18:00 GO/NO-GO Keycloak | D12: 21:00 Daily | E12: 09:00 Daily | G12: 21:00 Daily 22:00 Backend de seguridad completo | H12: 09:00 Daily 12:00 Enlace público | I12: 18:00 CODE FREEZE | J12: 19:00 Secciones del informe 20:00 Diapositivas de cada uno 21:30 Ensayo 23:00 PDF + presentación 23:59 LMS | K12: 07:00 Ensayo final PRESENTACIÓN | L12: Entrega 2

Sheet Dependencias
A1: Dependencias y ruta crítica
A2: Si una tarea de la ruta crítica se atrasa, se atrasa la entrega. Prioridad de ayuda: primero desbloquear la ruta crítica.
A4: Ruta crítica hasta la entrega del lunes (ENT-03)
A5: 27 h encadenadas | B5: C-01 (Nicole, Sáb 10 10:00) → IAM-01 (Nicole, Sáb 10 18:00) → IAM-02 (Nicole, Sáb 10 22:00) → IAM-03 (Nicole, Dom 11 17:00) → IAM-05 (Nicole, Dom 11 22:00) → LOG-02 (Alvaro, Lun 12 13:00) → LOG-04 (Alvaro, Lun 12 17:00) → INF-07 (Alvaro, Lun 12 19:00) → INF-09 (Alan, Lun 12 23:00) → ENT-03 (Alan, Lun 12 23:59)
A7: Cadenas por frente
A8: Frente | B8: Cadena (→ = «debe terminar antes que»)
A9: Identidad y contraseñas | B9: C-01 → IAM-01 (go/no-go 18:00) → IAM-02 → IAM-03 → IAM-05 → IAM-06 → C-03 (code freeze) → C-04 (ensayo). PO-03 (valores de la política) → IAM-02. IAM-01 → IAM-04 → IAM-05. Si IAM-01 = no-go → IAM-07.
A10: Roles y autorización | B10: C-01 → RBAC-01 → RBAC-02 → RBAC-05 → INF-04. RBAC-01 → RBAC-03 → RBAC-04 → VULN-02 → INF-08. RBAC-01 → RBAC-06 → INF-04.
A11: Hardening y escaneo | B11: VULN-01 (antes) → HARD-01 / HARD-02 / HARD-03 / HARD-04 → VULN-02 (después) → INF-08 → INF-09. HARD-01 + IAM-03 → DEP-01 → C-03.
A12: Criptografía e integridad | B12: CRY-01 → PO-05. CRY-01 + CRY-02 + CRY-03 → CRY-04 → INF-09. CRY-02 + CRY-03 → PR-05.
A13: Logs de seguridad | B13: LOG-01 + IAM-04 + IAM-05 + RBAC-02 → LOG-02 → LOG-04 → INF-07. LOG-02 → PR-06.
A14: Clasificación de la información | B14: C-01 → GRC-01 (inventario) → GRC-02 (formulario) → GRC-03 (matriz) → INF-09. GRC-02 → MOD15-01 (módulo 15). GRC-01 → RSK-01 (riesgos).
A15: ISO 27002 y brechas | B15: ISO-01 (2022) → ISO-02 (2013 + mapeo). ISO-01 → ISO-03 (fichas de brechas) → INF-09.
A16: Políticas y procedimientos | B16: C-01 → GRC-00 (plantilla) → todas las PO-xx y PR-xx. Cada procedimiento espera además a la funcionalidad que documenta (ej. PR-02 espera a IAM-05).
A17: Informe y entregables | B17: C-01 → INF-00 → INF-01. Todas las INF-0x + RSK-01 + MOD15-01 + ISO-01/03 + GRC-03 + CRY-04 + RBAC-06 → INF-09 → ENT-03 (LMS). INF-02 → ENT-01 → C-04. C-02 + INF-09 → ENT-02 (póster).
A19: Tareas que más bloquean (desbloquear primero)
A20: Tarea | B20: Bloquea directamente a
A21: GRC-00 — Favian | B21: 16 tareas: GRC-02, PO-01, PO-02, PO-03, PO-04, PO-05, PO-06, PO-07, PR-01, PR-02, PR-03, PR-04, PR-05, PR-06, PR-07, PR-08
A22: C-01 — Nicole | B22: 9 tareas: IAM-01, IAM-04, PWM-01, RBAC-01, GRC-00, GRC-01, MOD15-01, PO-03, INF-00
A23: VULN-01 — Juanjo | B23: 6 tareas: HARD-01, HARD-02, HARD-03, HARD-04, PO-07, PR-04
A24: HARD-01 — Juanjo | B24: 6 tareas: HARD-05, VULN-02, DEP-01, INF-02, INF-05, INF-06
A25: IAM-01 — Nicole | B25: 4 tareas: IAM-02, IAM-04, IAM-07, PWM-01
A26: IAM-04 — Nicole | B26: 4 tareas: IAM-05, IAM-06, LOG-02, PR-01
A27: IAM-05 — Nicole | B27: 4 tareas: IAM-06, LOG-02, PR-02, INF-02
A28: RBAC-01 — Franco | B28: 4 tareas: RBAC-02, RBAC-03, RBAC-06, PO-02
A29: HARD-03 — Juanjo | B29: 4 tareas: VULN-02, INF-02, INF-05, INF-06
A30: CRY-02 — Alvaro | B30: 4 tareas: C-03, CRY-04, PR-05, INF-02

Sheet Cobertura PDF
A1: Trazabilidad: exigencias del PDF y documentos extra → tareas
A2: Fuente: «PROYECTO DE SEGURIDAD DE SISTEMAS 2025.pdf» (Mgr. Ing. Lourdes Peredo Quiroga) + documentos pedidos por la docente al equipo.
A4: Ref. | B4: Exigencia | C4: Tareas que la cubren | D4: Responsable principal
A5: 1 | B5: Carátula | C5: INF-00, INF-01 | D5: Alan
A6: 2–7 | B6: Introducción, nombre y descripción, objetivo, tecnología, problemas que resuelve, módulos | C6: INF-01 | D6: Alan
A7: 8 | B7: Alcance de la reingeniería (todo lo de seguridad añadido o corregido) | C7: INF-02 (+ todas las tareas de código) | D7: Alan
A8: 9.1 | B8: ABM de usuarios con User ID de formato estándar | C8: IAM-04, IAM-06, PR-01, INF-03 | D8: Nicole
A9: 9.2 | B9: Gestión de roles (altas, bajas, asignación) desde la aplicación, granular | C9: RBAC-01, RBAC-02, RBAC-03, RBAC-05, PR-03, PO-02, INF-04 | D9: Franco
A10: 9.2 | B10: Matriz de accesos en plantilla + demostración en el sistema | C10: RBAC-06, RBAC-05 | D10: Franco
A11: 9.3 | B11: Complejidad y longitud de contraseña | C11: PO-03, IAM-02 | D11: Nicole
A12: 9.3 | B12: Tiempo de vida útil y control de histórico | C12: PO-03, IAM-02, IAM-05 | D12: Nicole
A13: 9.3 | B13: Bloqueo al tercer intento, DESBLOQUEO y REINICIO | C13: IAM-02, IAM-03, IAM-05, PR-02 | D13: Nicole
A14: 9.3 | B14: Protocolo de encriptación utilizado | C14: CRY-01, CRY-04, INF-03 | D14: Alvaro
A15: 9.3 | B15: Uso de gestor de contraseñas para el resguardo | C15: PWM-01, PR-08 | D15: Favian
... A45: Extra | B45: Integridad de archivos por hash y checksum aplicada a MedicalSys | C45: CRY-02, CRY-03, PR-05 | D45: Alvaro

Sheet Documentos
A1: Catálogo de documentos a producir
A2: Responsable, vencimiento y estado se calculan desde la hoja Tareas (no editar aquí). Guardar cada archivo en la carpeta indicada.
A4: Código | B4: Documento | C4: Tipo | D4: Tarea | E4: Archivo sugerido | F4: Carpeta | G4: Responsable | H4: Vence | I4: Estado
A5: PO-01 | B5: Política general de seguridad de la información | C5: Política | D5: PO-01 | E5: PO-01_Politica_General_SI.docx | F5: 02-Políticas | G5: =IFERROR(INDEX(Tareas!$D$5:$D$77,MATCH($D5,Tareas!$A$5:$A$77,0)),"") | H5: =IFERROR(INDEX(Tareas!$J$5:$J$77,MATCH($D5,Tareas!$A$5:$A$77,0)),"") | I5: =IFERROR(INDEX(Tareas!$S$5:$S$77,MATCH($D5,Tareas!$A$5:$A$77,0)),"")
A6: PO-02 | B6: Política de control de acceso | C6: Política | D6: PO-02 | E6: PO-02_Control_Acceso.docx | F6: 02-Políticas | G6: =IFERROR(INDEX(Tareas!$D$5:$D$77,MATCH($D6,Tareas!$A$5:$A$77,0)),"") | H6: =IFERROR(INDEX(Tareas!$J$5:$J$77,MATCH($D6,Tareas!$A$5:$A$77,0)),"") | I6: =IFERROR(INDEX(Tareas!$S$5:$S$77,MATCH($D6,Tareas!$A$5:$A$77,0)),"")
A7: PO-03 | B7: Política de contraseñas y autenticación | C7: Política | D7: PO-03 | E7: PO-03_Contrasenas.docx | F7: 02-Políticas | G7: =IFERROR(INDEX(Tareas!$D$5:$D$77,MATCH($D7,Tareas!$A$5:$A$77,0)),"") | H7: =IFERROR(INDEX(Tareas!$J$5:$J$77,MATCH($D7,Tareas!$A$5:$A$77,0)),"") | I7: =IFERROR(INDEX(Tareas!$S$5:$S$77,MATCH($D7,Tareas!$A$5:$A$77,0)),"")
A8: PO-04 | B8: Política de clasificación y manejo de la información | C8: Política | D8: PO-04 | E8: PO-04_Clasificacion.docx | F8: 02-Políticas | G8: =IFERROR(INDEX(Tareas!$D$5:$D$77,MATCH($D8,Tareas!$A$5:$A$77,0)),"") | H8: =IFERROR(INDEX(Tareas!$J$5:$J$77,MATCH($D8,Tareas!$A$5:$A$77,0)),"") | I8: =IFERROR(INDEX(Tareas!$S$5:$S$77,MATCH($D8,Tareas!$A$5:$A$77,0)),"")
A9: PO-05 | B9: Política criptográfica y de gestión de claves | C9: Política | D9: PO-05 | E9: PO-05_Criptografia.docx | F9: 02-Políticas | G9: =IFERROR(INDEX(Tareas!$D$5:$D$77,MATCH($D9,Tareas!$A$5:$A$77,0)),"") | H9: =IFERROR(INDEX(Tareas!$J$5:$J$77,MATCH($D9,Tareas!$A$5:$A$77,0)),"") | I9: =IFERROR(INDEX(Tareas!$S$5:$S$77,MATCH($D9,Tareas!$A$5:$A$77,0)),"")
A10: PO-06 | B10: Política de registro y monitoreo (logs) | C10: Política | D10: PO-06 | E10: PO-06_Logs.docx | F10: 02-Políticas | G10: =IFERROR(INDEX(Tareas!$D$5:$D$77,MATCH($D10,Tareas!$A$5:$A$77,0)),"") | H10: =IFERROR(INDEX(Tareas!$J$5:$J$77,MATCH($D10,Tareas!$A$5:$A$77,0)),"") | I10: =IFERROR(INDEX(Tareas!$S$5:$S$77,MATCH($D10,Tareas!$A$5:$A$77,0)),"")
A11: PO-07 | B11: Política de gestión de vulnerabilidades y desarrollo seguro | C11: Política | D11: PO-07 | E11: PO-07_Vulnerabilidades.docx | F11: 02-Políticas | G11: =IFERROR(INDEX(Tareas!$D$5:$D$77,MATCH($D11,Tareas!$A$5:$A$77,0)),"") | H11: =IFERROR(INDEX(Tareas!$J$5:$J$77,MATCH($D11,Tareas!$A$5:$A$77,0)),"") | I11: =IFERROR(INDEX(Tareas!$S$5:$S$77,MATCH($D11,Tareas!$A$5:$A$77,0)),"")
A12: PR-01 | B12: Procedimiento de ABM de usuarios | C12: Procedimiento | D12: PR-01 | E12: PR-01_ABM_Usuarios.docx | F12: 03-Procedimientos | G12: =IFERROR(INDEX(Tareas!$D$5:$D$77,MATCH($D12,Tareas!$A$5:$A$77,0)),"") | H12: =IFERROR(INDEX(Tareas!$J$5:$J$77,MATCH($D12,Tareas!$A$5:$A$77,0)),"") | I12: =IFERROR(INDEX(Tareas!$S$5:$S$77,MATCH($D12,Tareas!$A$5:$A$77,0)),"")
A13: PR-02 | B13: Procedimiento de desbloqueo y reinicio de contraseña | C13: Procedimiento | D13: PR-02 | E13: PR-02_Desbloqueo_Reinicio.docx | F13: 03-Procedimientos | G13: =IFERROR(INDEX(Tareas!$D$5:$D$77,MATCH($D13,Tareas!$A$5:$A$77,0)),"") | H13: =IFERROR(INDEX(Tareas!$J$5:$J$77,MATCH($D13,Tareas!$A$5:$A$77,0)),"") | I13: =IFERROR(INDEX(Tareas!$S$5:$S$77,MATCH($D13,Tareas!$A$5:$A$77,0)),"")
A14: PR-03 | B14: Procedimiento de asignación/revocación de roles y revisión de accesos | C14: Procedimiento | D14: PR-03 | E14: PR-03_Roles.docx | F14: 03-Procedimientos | G14: =IFERROR(INDEX(Tareas!$D$5:$D$77,MATCH($D14,Tareas!$A$5:$A$77,0)),"") | H14: =IFERROR(INDEX(Tareas!$J$5:$J$77,MATCH($D14,Tareas!$A$5:$A$77,0)),"") | I14: =IFERROR(INDEX(Tareas!$S$5:$S$77,MATCH($D14,Tareas!$A$5:$A$77,0)),"")
A15: PR-04 | B15: Procedimiento de gestión de vulnerabilidades | C15: Procedimiento | D15: PR-04 | E15: PR-04_Vulnerabilidades.docx | F15: 03-Procedimientos | G15: =IFERROR(INDEX(Tareas!$D$5:$D$77,MATCH($D15,Tareas!$A$5:$A$77,0)),"") | H15: =IFERROR(INDEX(Tareas!$J$5:$J$77,MATCH($D15,Tareas!$A$5:$A$77,0)),"") | I15: =IFERROR(INDEX(Tareas!$S$5:$S$77,MATCH($D15,Tareas!$A$5:$A$77,0)),"")
A16: PR-05 | B16: Procedimiento de verificación de integridad (hash/checksum) | C16: Procedimiento | D16: PR-05 | E16: PR-05_Integridad.docx | F16: 03-Procedimientos | G16: =IFERROR(INDEX(Tareas!$D$5:$D$77,MATCH($D16,Tareas!$A$5:$A$77,0)),"") | H16: =IFERROR(INDEX(Tareas!$J$5:$J$77,MATCH($D16,Tareas!$A$5:$A$77,0)),"") | I16: =IFERROR(INDEX(Tareas!$S$5:$S$77,MATCH($D16,Tareas!$A$5:$A$77,0)),"")
... A34: POS | B34: Póster digital | C34: Póster | D34: ENT-02 | E34: Poster_NombreGrupo.pdf | F34: 10-Presentación-Póster | G34: =IFERROR(INDEX(Tareas!$D$5:$D$77,MATCH($D34,Tareas!$A$5:$A$77,0)),"") | H34: =IFERROR(INDEX(Tareas!$J$5:$J$77,MATCH($D34,Tareas!$A$5:$A$77,0)),"") | I34: =IFERROR(INDEX(Tareas!$S$5:$S$77,MATCH($D34,Tareas!$A$5:$A$77,0)),"")

Sheet Decisiones
A1: Decisiones del kickoff (sáb 10, 9:00)
A2: Columna amarilla = completar en la reunión. Las propuestas ya vienen cargadas para decidir rápido.
A4: Tema | B4: Propuesta | C4: Decisión final | D4: Tarea | E4: Justificación / nota
A5: Longitud de contraseña | B5: Mínimo 12, máximo 64 caracteres | D5: IAM-02, PO-03 | E5: La longitud aporta más entropía que la complejidad (NIST SP 800-63B).
A6: Complejidad | B6: Al menos 1 mayúscula, 1 minúscula, 1 dígito y 1 carácter especial; no puede contener el usuario ni el correo | D6: IAM-02, PO-03 | E6: Lo exige el punto 9.3 del PDF.
A7: Vida útil | B7: 90 días (cambio forzado al vencer) | D7: IAM-02, PO-03 | E7: Lo exige el PDF. Matiz para la defensa: NIST ya no recomienda la expiración periódica salvo sospecha de compromiso.
A8: Histórico | B8: No reutilizar las últimas 5 | D8: IAM-02, PO-03
A9: Bloqueo | B9: Al 3er intento fallido; bloqueo permanente hasta que lo desbloquee un administrador | D9: IAM-02, PO-03 | E9: El PDF pide «bloqueo al tercer intento, DESBLOQUEO».
A10: Reinicio | B10: Contraseña temporal + cambio obligatorio en el primer inicio de sesión | D10: IAM-05, PR-02
A11: Almacenamiento | B11: Argon2id (Keycloak) + TLS en tránsito | D11: IAM-02, CRY-01 | E11: Función memory-hard y con sal, resistente a GPU.
A12: Formato del User ID | B12: MS-AA-NNNNN (ej. MS-26-00001): prefijo, año de alta, correlativo; único, inmutable, nunca reutilizado, independiente del rol | D12: IAM-04 | E12: Si el código dependiera del rol, cambiaría al cambiar de rol y se perdería la trazabilidad.
A13: Herramienta externa de identidad | B13: Keycloak (lo que llamaron «keylog»): IAM open source con políticas de contraseñas, bloqueo por fuerza bruta y passkeys | D13: IAM-01 | E13: Un keylogger es malware: no confundir los nombres en el informe.
A14: Gestor de contraseñas (resguardo) | B14: KeePassXC (bóveda cifrada AES-256/ChaCha20 + Argon2 + archivo llave) | D14: PWM-01 | E14: Sin servidor, gratis y suficiente para 6 personas. Alternativa: Bitwarden.
A15: Tema del módulo 15 | B15: Herramienta automatizada de clasificación de activos (formulario → nivel → matriz → dashboard) | D15: MOD15-01 | E15: Reutiliza GRC-01/02/03. Alternativa: evaluador de cumplimiento ISO 27002.
A16: Nombre del grupo en los archivos | B16: ProyLos6Siniestros-1.pdf / PresLos6Siniestros-1.pdf | D16: INF-09, ENT-01 | E16: Confirmar el nombre oficial del grupo ante la docente.
A17: Carpeta compartida | B17: Google Drive «SIS321-MedicalSys» con 01-Informe … 10-Presentación-Póster | D17: GRC-00
A18: Convención de ramas | B18: seg/<ID>-descripcion → PR a develop con revisión cruzada | D18: C-03
A19: Dailies | B19: 9:00 y 21:00, 15 minutos | D19: C-01
A20: Prioridad frente a DoggyCredit S3 | B20: Horas por día para cada proyecto: a definir | D20: C-01 | E20: El mismo equipo tiene ese sprint hasta el martes 13.
A21: ¿El martes es la defensa? (docente) | D21: C-02 | E21: Si lo es, la entrega 1 se sube al LMS el domingo 11.
A22: Formato del póster (docente) | D22: C-02
A23: Versión ISO 27002 esperada (docente) | B23: Hacemos ambas: 2022 completa y 2013 vía mapeo | D23: C-02
A25: Ejemplo de llenado | C25: «Aprobado tal cual» o el valor acordado, p. ej. «12 caracteres»

Sheet Defensa
A1: Banco de preguntas para la defensa individual (60 % de la nota)
A2: Todos deben poder responder TODAS. El «experto» prepara la respuesta modelo y la explica al resto en el ensayo (C-04).
A4: N° | B4: Tema | C4: Pregunta | D4: Puntos clave de la respuesta | E4: Experto | F4: ¿Dominada?
A5: 1 | B5: Principios | C5: ¿Qué es la mediación completa y cómo la violaba MedicalSys? | D5: Todo acceso a todo recurso se verifica siempre. Antes: los microservicios publicaban sus puertos y confiaban en X-Roles/X-Organization-Id, así que con un curl directo se saltaba el gateway; además, el logout no revocaba el token fuera de identidad. Corrección: red interna (HARD-01) y verificación del jti en el gateway (HARD-02). | E5: Juanjo
A6: 2 | B6: Principios | C6: Seguridad por defecto (fail-safe defaults): da 2 ejemplos del sistema. | D6: El interceptor permitía los endpoints sin anotación y ahora los deniega (RBAC-04). El webhook no verificaba la firma si faltaba el secreto y ahora el servicio no arranca (HARD-03). Usuarios demo apagados por defecto. | E6: Franco
A7: 3 | B7: Principios | C7: Mínimo privilegio vs segregación de roles: ¿en qué se diferencian? | D7: Mínimo privilegio: cada sujeto tiene solo los permisos necesarios (permisos granulares por funcionalidad). Segregación: una tarea crítica requiere a más de una persona o rol (nadie se asigna permisos a sí mismo; el acceso a otro tenant necesita la solicitud de la clínica y el OTP del paciente). | E7: Franco
A8: 4 | B8: Principios | C8: ¿Qué es el «menos asombro» (aceptabilidad psicológica) y dónde se aplicó? | D8: La seguridad no debe sorprender ni estorbar al usuario, o este la evade. Un único login, mensajes claros cuando la contraseña no cumple la política, bloqueo explicado y desbloqueo por el administrador. | E8: Nicole
A9: 5 | B9: Principios | C9: ¿Qué es el «mecanismo menos común» y qué se compartía de más? | D9: Minimizar los mecanismos compartidos entre usuarios o componentes. Se compartían el mismo usuario de BD para 13 servicios, el secreto JWT con el gateway y un único secreto de servicio. Mejoras: un usuario de BD por servicio (HARD-05), secretos rotados en la bóveda y una DEK por tenant. | E9: Juanjo
A10: 6 | B10: Principios | C10: Nombra los 8 principios de Saltzer y Schroeder (1975). | D10: Economía del mecanismo, valores por defecto seguros, mediación completa, diseño abierto, separación de privilegios, mínimo privilegio, mínimo mecanismo común y aceptabilidad psicológica (+ factor de trabajo y registro de compromisos). | E10: Franco
A11: 7 | B11: Contraseñas | C11: ¿Por qué Argon2id y no SHA-256 para guardar contraseñas? | D11: SHA-256 es rápido: una GPU prueba miles de millones por segundo. Argon2id es lento a propósito, memory-hard (encarece GPU/ASIC) y usa sal por usuario contra las tablas arcoíris. | E11: Nicole
A12: 8 | B12: Contraseñas | C12: Explica cada regla de la política y su justificación. | D12: Longitud ≥ 12 (entropía), complejidad (exigida por el curso), 90 días (exigido; NIST lo desaconseja salvo compromiso), historial de 5 (evita rotar entre dos contraseñas), bloqueo al 3er intento (fuerza bruta online), desbloqueo por el administrador (verifica la identidad). | E12: Nicole
A13: 9 | B13: Contraseñas | C13: ¿Qué pasa al 3er intento fallido y cómo se recupera la cuenta? | D13: Keycloak marca la cuenta como bloqueada (brute force detection, permanentLockout). El login responde 423 y queda el evento ACCOUNT_LOCKED. Un administrador con identity.user.unlock la desbloquea desde la app; opcionalmente se reinicia con contraseña temporal y cambio obligatorio. | E13: Nicole
A14: 10 | B14: Contraseñas | C14: ¿Qué es Keycloak y por qué usar una herramienta externa? | D14: IAM open source (OIDC/OAuth2) que centraliza cuentas, políticas de contraseñas, bloqueo y passkeys. Ventajas: diseño abierto y probado, menos código propio de seguridad (economía del mecanismo) y estandarización. | E14: Nicole
A15: 11 | B15: Contraseñas | C15: ¿Cómo protege KeePassXC la bóveda y por qué un gestor de contraseñas? | D15: Cifra con AES-256 o ChaCha20 y deriva la clave con Argon2 a partir de la contraseña maestra y un archivo llave. Permite contraseñas largas y únicas por servicio sin memorizarlas, y evita secretos en chats o archivos .env compartidos. | E15: Favian
A16: 12 | B16: Usuarios | C16: ¿Por qué el User ID tiene formato estándar, es inmutable y no se reutiliza? | D16: Trazabilidad: los logs y la auditoría referencian al usuario para siempre. Si se reutiliza o cambia con el rol, se pierde la atribución de las acciones (no repudio). | E16: Nicole
... A34: 30 | B34: Módulo 15 | C34: ¿Qué automatiza su módulo 15 y por qué fuera del sistema? | D34: Automatiza la clasificación de activos (formulario → nivel → matriz → dashboard). Va fuera de MedicalSys porque es una herramienta de gestión de seguridad de la información de la organización, no una función clínica. | E34: Favian
